{
"meta":{"test_sets":[],"test_metrics":[],"learn_metrics":[{"best_value":"Min","name":"RMSE"}],"launch_mode":"Train","parameters":"","iteration_count":1000,"learn_sets":["learn"],"name":"experiment"},
"iterations":[
{"learn":[0.8621766786],"iteration":0,"passed_time":0.0257913339,"remaining_time":25.76554256},
{"learn":[0.7728719993],"iteration":1,"passed_time":0.04048105107,"remaining_time":20.20004448},
{"learn":[0.6938938811],"iteration":2,"passed_time":0.05488290858,"remaining_time":18.23941995},
{"learn":[0.623203506],"iteration":3,"passed_time":0.06843176989,"remaining_time":17.0395107},
{"learn":[0.5604753491],"iteration":4,"passed_time":0.0815564038,"remaining_time":16.22972436},
{"learn":[0.5043247454],"iteration":5,"passed_time":0.09474478432,"remaining_time":15.6960526},
{"learn":[0.4539734284],"iteration":6,"passed_time":0.1095402042,"remaining_time":15.53906039},
{"learn":[0.4102056995],"iteration":7,"passed_time":0.1233867163,"remaining_time":15.29995282},
{"learn":[0.3710176797],"iteration":8,"passed_time":0.1384038327,"remaining_time":15.2397998},
{"learn":[0.3360626066],"iteration":9,"passed_time":0.151403015,"remaining_time":14.98889848},
{"learn":[0.305615886],"iteration":10,"passed_time":0.1646181024,"remaining_time":14.80066393},
{"learn":[0.2780322816],"iteration":11,"passed_time":0.1783965765,"remaining_time":14.68798479},
{"learn":[0.2533673298],"iteration":12,"passed_time":0.1913582191,"remaining_time":14.52850479},
{"learn":[0.2318301999],"iteration":13,"passed_time":0.2040992901,"remaining_time":14.37442143},
{"learn":[0.2121961639],"iteration":14,"passed_time":0.218919667,"remaining_time":14.3757248},
{"learn":[0.1949520142],"iteration":15,"passed_time":0.2325961048,"remaining_time":14.30466044},
{"learn":[0.179869921],"iteration":16,"passed_time":0.2448928662,"remaining_time":14.16056985},
{"learn":[0.166132041],"iteration":17,"passed_time":0.2584882666,"remaining_time":14.10197099},
{"learn":[0.1538264415],"iteration":18,"passed_time":0.2714909904,"remaining_time":14.0175085},
{"learn":[0.1431765103],"iteration":19,"passed_time":0.2844425502,"remaining_time":13.93768496},
{"learn":[0.1335337831],"iteration":20,"passed_time":0.2975513099,"remaining_time":13.87155869},
{"learn":[0.1251693522],"iteration":21,"passed_time":0.3099385248,"remaining_time":13.77817624},
{"learn":[0.1176598043],"iteration":22,"passed_time":0.3225388117,"remaining_time":13.70088778},
{"learn":[0.1113221623],"iteration":23,"passed_time":0.3356910275,"remaining_time":13.65143512},
{"learn":[0.1056309956],"iteration":24,"passed_time":0.3484755962,"remaining_time":13.59054825},
{"learn":[0.1007663334],"iteration":25,"passed_time":0.361476695,"remaining_time":13.54147311},
{"learn":[0.09653859052],"iteration":26,"passed_time":0.3736715451,"remaining_time":13.46601531},
{"learn":[0.09282110075],"iteration":27,"passed_time":0.3858439381,"remaining_time":13.39429671},
{"learn":[0.08946925],"iteration":28,"passed_time":0.3988266629,"remaining_time":13.35381689},
{"learn":[0.08663425482],"iteration":29,"passed_time":0.4110904677,"remaining_time":13.29192512},
{"learn":[0.08414192735],"iteration":30,"passed_time":0.4230591215,"remaining_time":13.22400932},
{"learn":[0.08180108221],"iteration":31,"passed_time":0.4360595954,"remaining_time":13.19080276},
{"learn":[0.07983042827],"iteration":32,"passed_time":0.4485533463,"remaining_time":13.1439723},
{"learn":[0.07810473876],"iteration":33,"passed_time":0.4607044071,"remaining_time":13.08942521},
{"learn":[0.07633146863],"iteration":34,"passed_time":0.473941785,"remaining_time":13.06725207},
{"learn":[0.07511054844],"iteration":35,"passed_time":0.4862491708,"remaining_time":13.02067224},
{"learn":[0.0738600492],"iteration":36,"passed_time":0.4986130536,"remaining_time":12.97741542},
{"learn":[0.07275330641],"iteration":37,"passed_time":0.5119527177,"remaining_time":12.96048722},
{"learn":[0.07173486889],"iteration":38,"passed_time":0.5246608738,"remaining_time":12.92818204},
{"learn":[0.07092970385],"iteration":39,"passed_time":0.5371227097,"remaining_time":12.89094503},
{"learn":[0.07012075788],"iteration":40,"passed_time":0.5496596666,"remaining_time":12.85667366},
{"learn":[0.06948947798],"iteration":41,"passed_time":0.5616141545,"remaining_time":12.81015143},
{"learn":[0.06892648981],"iteration":42,"passed_time":0.5738007134,"remaining_time":12.77040192},
{"learn":[0.06836776463],"iteration":43,"passed_time":0.5866528619,"remaining_time":12.74636673},
{"learn":[0.06782209799],"iteration":44,"passed_time":0.5997006665,"remaining_time":12.72698081},
{"learn":[0.06742031921],"iteration":45,"passed_time":0.6115544932,"remaining_time":12.6831084},
{"learn":[0.06697478751],"iteration":46,"passed_time":0.6250467742,"remaining_time":12.67382076},
{"learn":[0.06664528454],"iteration":47,"passed_time":0.6370718833,"remaining_time":12.63525902},
{"learn":[0.06629344002],"iteration":48,"passed_time":0.6500648993,"remaining_time":12.6165657},
{"learn":[0.0660460183],"iteration":49,"passed_time":0.6622897061,"remaining_time":12.58350442},
{"learn":[0.06581185735],"iteration":50,"passed_time":0.6737587199,"remaining_time":12.53719657},
{"learn":[0.06554054202],"iteration":51,"passed_time":0.6865773701,"remaining_time":12.51683359},
{"learn":[0.06530574298],"iteration":52,"passed_time":0.699683505,"remaining_time":12.50189206},
{"learn":[0.06514675142],"iteration":53,"passed_time":0.7102682326,"remaining_time":12.44284719},
{"learn":[0.06499620752],"iteration":54,"passed_time":0.7214406789,"remaining_time":12.39566257},
{"learn":[0.06483570347],"iteration":55,"passed_time":0.7338120613,"remaining_time":12.36997475},
{"learn":[0.06471135119],"iteration":56,"passed_time":0.745533145,"remaining_time":12.33399571},
{"learn":[0.06457972741],"iteration":57,"passed_time":0.7587093178,"remaining_time":12.32248582},
{"learn":[0.06445639954],"iteration":58,"passed_time":0.7711936109,"remaining_time":12.29988454},
{"learn":[0.06428779209],"iteration":59,"passed_time":0.7841480872,"remaining_time":12.2849867},
{"learn":[0.06418335279],"iteration":60,"passed_time":0.7962587335,"remaining_time":12.25716313},
{"learn":[0.06403143083],"iteration":61,"passed_time":0.8094421143,"remaining_time":12.24607586},
{"learn":[0.0639339362],"iteration":62,"passed_time":0.8214026435,"remaining_time":12.21673456},
{"learn":[0.06382256127],"iteration":63,"passed_time":0.8335879525,"remaining_time":12.19122381},
{"learn":[0.06375660575],"iteration":64,"passed_time":0.8451152965,"remaining_time":12.1566585},
{"learn":[0.06360580343],"iteration":65,"passed_time":0.8596912698,"remaining_time":12.16593403},
{"learn":[0.06353541754],"iteration":66,"passed_time":0.8712370295,"remaining_time":12.13230072},
{"learn":[0.06346212068],"iteration":67,"passed_time":0.8830516916,"remaining_time":12.1030026},
{"learn":[0.06335018338],"iteration":68,"passed_time":0.8969155361,"remaining_time":12.10186035},
{"learn":[0.06328971463],"iteration":69,"passed_time":0.9090370151,"remaining_time":12.07720606},
{"learn":[0.0632324899],"iteration":70,"passed_time":0.9218406245,"remaining_time":12.06183014},
{"learn":[0.06318988932],"iteration":71,"passed_time":0.9343930389,"remaining_time":12.04328806},
{"learn":[0.06307696796],"iteration":72,"passed_time":0.9488058958,"remaining_time":12.04853514},
{"learn":[0.06302180848],"iteration":73,"passed_time":0.9619320713,"remaining_time":12.03714997},
{"learn":[0.06294863018],"iteration":74,"passed_time":0.974221958,"remaining_time":12.01540415},
{"learn":[0.06289871674],"iteration":75,"passed_time":0.9870284422,"remaining_time":12.0001879},
{"learn":[0.06283154951],"iteration":76,"passed_time":0.9990841748,"remaining_time":11.97603498},
{"learn":[0.06274126482],"iteration":77,"passed_time":1.013101511,"remaining_time":11.9753794},
{"learn":[0.06268850997],"iteration":78,"passed_time":1.024932964,"remaining_time":11.94890202},
{"learn":[0.06259944273],"iteration":79,"passed_time":1.038343958,"remaining_time":11.94095551},
{"learn":[0.06255942074],"iteration":80,"passed_time":1.050264572,"remaining_time":11.91596472},
{"learn":[0.06249915578],"iteration":81,"passed_time":1.062259891,"remaining_time":11.89212903},
{"learn":[0.06245844336],"iteration":82,"passed_time":1.073758945,"remaining_time":11.86309582},
{"learn":[0.06235677301],"iteration":83,"passed_time":1.087766782,"remaining_time":11.86183777},
{"learn":[0.0623002657],"iteration":84,"passed_time":1.101441553,"remaining_time":11.85669437},
{"learn":[0.06227238418],"iteration":85,"passed_time":1.112854237,"remaining_time":11.82731131},
{"learn":[0.06221382358],"iteration":86,"passed_time":1.125024005,"remaining_time":11.8062864},
{"learn":[0.06215412691],"iteration":87,"passed_time":1.139286037,"remaining_time":11.8071462},
{"learn":[0.06212282313],"iteration":88,"passed_time":1.15571112,"remaining_time":11.82980708},
{"learn":[0.06208667201],"iteration":89,"passed_time":1.167653067,"remaining_time":11.8062699},
{"learn":[0.06202380632],"iteration":90,"passed_time":1.180697121,"remaining_time":11.79399652},
{"learn":[0.06197464805],"iteration":91,"passed_time":1.193238953,"remaining_time":11.77674967},
{"learn":[0.06193029775],"iteration":92,"passed_time":1.209651662,"remaining_time":11.79735545},
{"learn":[0.06187542069],"iteration":93,"passed_time":1.224634613,"remaining_time":11.80339319},
{"learn":[0.06182545098],"iteration":94,"passed_time":1.239655188,"remaining_time":11.80934679},
{"learn":[0.06179885361],"iteration":95,"passed_time":1.254922208,"remaining_time":11.81718412},
{"learn":[0.06176869337],"iteration":96,"passed_time":1.269814872,"remaining_time":11.8210601},
{"learn":[0.06173251204],"iteration":97,"passed_time":1.285446623,"remaining_time":11.83135565},
{"learn":[0.0616888761],"iteration":98,"passed_time":1.299432211,"remaining_time":11.82614567},
{"learn":[0.06165772364],"iteration":99,"passed_time":1.313269932,"remaining_time":11.81942938},
{"learn":[0.06162540241],"iteration":100,"passed_time":1.325112301,"remaining_time":11.79481147},
{"learn":[0.06157921348],"iteration":101,"passed_time":1.339433954,"remaining_time":11.79227148},
{"learn":[0.06155800913],"iteration":102,"passed_time":1.35101617,"remaining_time":11.76564568},
{"learn":[0.06151508624],"iteration":103,"passed_time":1.365780217,"remaining_time":11.76672187},
{"learn":[0.06149009246],"iteration":104,"passed_time":1.377324643,"remaining_time":11.74005291},
{"learn":[0.06144116756],"iteration":105,"passed_time":1.390774885,"remaining_time":11.72974289},
{"learn":[0.06140461334],"iteration":106,"passed_time":1.40403522,"remaining_time":11.71778926},
{"learn":[0.06136890287],"iteration":107,"passed_time":1.417230725,"remaining_time":11.70527599},
{"learn":[0.06133368693],"iteration":108,"passed_time":1.432337878,"remaining_time":11.7083766},
{"learn":[0.06130184548],"iteration":109,"passed_time":1.445779703,"remaining_time":11.69767215},
{"learn":[0.06127079525],"iteration":110,"passed_time":1.458494067,"remaining_time":11.68109213},
{"learn":[0.06124056564],"iteration":111,"passed_time":1.474916776,"remaining_time":11.69398301},
{"learn":[0.06120021192],"iteration":112,"passed_time":1.48928126,"remaining_time":11.69019892},
{"learn":[0.06116163953],"iteration":113,"passed_time":1.503784029,"remaining_time":11.68730394},
{"learn":[0.06112798374],"iteration":114,"passed_time":1.515970171,"remaining_time":11.66637914},
{"learn":[0.06110772494],"iteration":115,"passed_time":1.527335982,"remaining_time":11.63935352},
{"learn":[0.06107531235],"iteration":116,"passed_time":1.540426326,"remaining_time":11.62561065},
{"learn":[0.06104981783],"iteration":117,"passed_time":1.552421729,"remaining_time":11.60369462},
{"learn":[0.06102209077],"iteration":118,"passed_time":1.565217463,"remaining_time":11.58787046},
{"learn":[0.06099163651],"iteration":119,"passed_time":1.578844946,"remaining_time":11.57819627},
{"learn":[0.06096358454],"iteration":120,"passed_time":1.591791797,"remaining_time":11.56351231},
{"learn":[0.06094462284],"iteration":121,"passed_time":1.607146979,"remaining_time":11.56618891},
{"learn":[0.06091216205],"iteration":122,"passed_time":1.620470102,"remaining_time":11.55408358},
{"learn":[0.06088332123],"iteration":123,"passed_time":1.635450429,"remaining_time":11.55366593},
{"learn":[0.0608601515],"iteration":124,"passed_time":1.647145347,"remaining_time":11.53001743},
{"learn":[0.06083682638],"iteration":125,"passed_time":1.659176165,"remaining_time":11.50888863},
{"learn":[0.0608046863],"iteration":126,"passed_time":1.674089703,"remaining_time":11.50771898},
{"learn":[0.06077272018],"iteration":127,"passed_time":1.688358651,"remaining_time":11.50194331},
{"learn":[0.06074504887],"iteration":128,"passed_time":1.700459923,"remaining_time":11.48139994},
{"learn":[0.06073130507],"iteration":129,"passed_time":1.71325095,"remaining_time":11.46560251},
{"learn":[0.06070086957],"iteration":130,"passed_time":1.727203998,"remaining_time":11.45755934},
{"learn":[0.06067651845],"iteration":131,"passed_time":1.741034469,"remaining_time":11.4486206},
{"learn":[0.060655419],"iteration":132,"passed_time":1.754017027,"remaining_time":11.43408092},
{"learn":[0.06063191134],"iteration":133,"passed_time":1.767005877,"remaining_time":11.41960514},
{"learn":[0.06061615344],"iteration":134,"passed_time":1.779400716,"remaining_time":11.40134533},
{"learn":[0.06059719564],"iteration":135,"passed_time":1.79255289,"remaining_time":11.38798307},
{"learn":[0.06058050211],"iteration":136,"passed_time":1.804315555,"remaining_time":11.36587098},
{"learn":[0.06055175679],"iteration":137,"passed_time":1.817581098,"remaining_time":11.35329642},
{"learn":[0.06053654175],"iteration":138,"passed_time":1.831074421,"remaining_time":11.34212285},
{"learn":[0.06052638072],"iteration":139,"passed_time":1.842128707,"remaining_time":11.31593348},
{"learn":[0.06050051889],"iteration":140,"passed_time":1.854569252,"remaining_time":11.29840417},
{"learn":[0.06047705372],"iteration":141,"passed_time":1.869716903,"remaining_time":11.29730354},
{"learn":[0.06046129341],"iteration":142,"passed_time":1.88278979,"remaining_time":11.28357238},
{"learn":[0.06043299561],"iteration":143,"passed_time":1.895737017,"remaining_time":11.26910338},
{"learn":[0.06040970404],"iteration":144,"passed_time":1.909207924,"remaining_time":11.25774327},
{"learn":[0.06038826028],"iteration":145,"passed_time":1.922614084,"remaining_time":11.24597553},
{"learn":[0.06037149401],"iteration":146,"passed_time":1.935700887,"remaining_time":11.23233236},
{"learn":[0.06034817613],"iteration":147,"passed_time":1.948885393,"remaining_time":11.21925915},
{"learn":[0.06033194717],"iteration":148,"passed_time":1.963355538,"remaining_time":11.21352727},
{"learn":[0.06031997589],"iteration":149,"passed_time":1.975561179,"remaining_time":11.19484668},
{"learn":[0.06029892042],"iteration":150,"passed_time":1.990046782,"remaining_time":11.18907098},
{"learn":[0.06028525948],"iteration":151,"passed_time":2.004795371,"remaining_time":11.18464786},
{"learn":[0.06026726721],"iteration":152,"passed_time":2.019880984,"remaining_time":11.18195551},
{"learn":[0.06024917828],"iteration":153,"passed_time":2.035177961,"remaining_time":11.18026334},
{"learn":[0.06023201615],"iteration":154,"passed_time":2.048964434,"remaining_time":11.17016095},
{"learn":[0.06021462645],"iteration":155,"passed_time":2.060968045,"remaining_time":11.15036557},
{"learn":[0.06019814267],"iteration":156,"passed_time":2.073217142,"remaining_time":11.13198758},
{"learn":[0.06017982391],"iteration":157,"passed_time":2.084914435,"remaining_time":11.11074655},
{"learn":[0.06016713452],"iteration":158,"passed_time":2.09638549,"remaining_time":11.08842892},
{"learn":[0.06014746614],"iteration":159,"passed_time":2.111257615,"remaining_time":11.08410248},
{"learn":[0.06012993629],"iteration":160,"passed_time":2.126022828,"remaining_time":11.0790879},
{"learn":[0.06011416785],"iteration":161,"passed_time":2.138074769,"remaining_time":11.05991763},
{"learn":[0.06010186824],"iteration":162,"passed_time":2.150969915,"remaining_time":11.04516453},
{"learn":[0.06008460123],"iteration":163,"passed_time":2.163907059,"remaining_time":11.03064818},
{"learn":[0.06006539332],"iteration":164,"passed_time":2.177242307,"remaining_time":11.01816561},
{"learn":[0.06004608021],"iteration":165,"passed_time":2.192911763,"remaining_time":11.01740006},
{"learn":[0.06003609951],"iteration":166,"passed_time":2.20647454,"remaining_time":11.00594786},
{"learn":[0.06002925983],"iteration":167,"passed_time":2.218616143,"remaining_time":10.98743233},
{"learn":[0.06001581246],"iteration":168,"passed_time":2.233294986,"remaining_time":10.98146825},
{"learn":[0.0600022535],"iteration":169,"passed_time":2.245742781,"remaining_time":10.96450887},
{"learn":[0.05998695747],"iteration":170,"passed_time":2.257527361,"remaining_time":10.94438703},
{"learn":[0.05997609055],"iteration":171,"passed_time":2.269467059,"remaining_time":10.92510886},
{"learn":[0.05996344986],"iteration":172,"passed_time":2.282749184,"remaining_time":10.9123328},
{"learn":[0.05994704752],"iteration":173,"passed_time":2.294702922,"remaining_time":10.89324491},
{"learn":[0.0599357035],"iteration":174,"passed_time":2.308601598,"remaining_time":10.88340753},
{"learn":[0.05992633456],"iteration":175,"passed_time":2.319615844,"remaining_time":10.86001964},
{"learn":[0.05991313857],"iteration":176,"passed_time":2.333985495,"remaining_time":10.85237324},
{"learn":[0.059900383],"iteration":177,"passed_time":2.34956304,"remaining_time":10.85022932},
{"learn":[0.05988370694],"iteration":178,"passed_time":2.367093648,"remaining_time":10.85689321},
{"learn":[0.05987337675],"iteration":179,"passed_time":2.3889439,"remaining_time":10.88296665},
{"learn":[0.05985815395],"iteration":180,"passed_time":2.407159762,"remaining_time":10.89206544},
{"learn":[0.05984950291],"iteration":181,"passed_time":2.419859961,"remaining_time":10.87607389},
{"learn":[0.05983432161],"iteration":182,"passed_time":2.43781617,"remaining_time":10.88358367},
{"learn":[0.05982241243],"iteration":183,"passed_time":2.449853071,"remaining_time":10.86456579},
{"learn":[0.05980586769],"iteration":184,"passed_time":2.463074574,"remaining_time":10.85084204},
{"learn":[0.05979132249],"iteration":185,"passed_time":2.47741856,"remaining_time":10.84203606},
{"learn":[0.05978194697],"iteration":186,"passed_time":2.490016764,"remaining_time":10.8255809},
{"learn":[0.05976679298],"iteration":187,"passed_time":2.502841997,"remaining_time":10.81014735},
{"learn":[0.05975252474],"iteration":188,"passed_time":2.516047876,"remaining_time":10.79637475},
{"learn":[0.05973838833],"iteration":189,"passed_time":2.528756574,"remaining_time":10.78048855},
{"learn":[0.0597253838],"iteration":190,"passed_time":2.542581462,"remaining_time":10.76936337},
{"learn":[0.05971611892],"iteration":191,"passed_time":2.555792383,"remaining_time":10.75562628},
{"learn":[0.05970812301],"iteration":192,"passed_time":2.568470666,"remaining_time":10.7396675},
{"learn":[0.05969725219],"iteration":193,"passed_time":2.582649535,"remaining_time":10.72997694},
{"learn":[0.05968418503],"iteration":194,"passed_time":2.594967796,"remaining_time":10.71255936},
{"learn":[0.05966893653],"iteration":195,"passed_time":2.610602879,"remaining_time":10.70879957},
{"learn":[0.05965417737],"iteration":196,"passed_time":2.623105213,"remaining_time":10.69214967},
{"learn":[0.05964362647],"iteration":197,"passed_time":2.634924625,"remaining_time":10.6727755},
{"learn":[0.05963851546],"iteration":198,"passed_time":2.646540547,"remaining_time":10.65265818},
{"learn":[0.05961899537],"iteration":199,"passed_time":2.660914198,"remaining_time":10.64365679},
{"learn":[0.05960803108],"iteration":200,"passed_time":2.674112911,"remaining_time":10.62993142},
{"learn":[0.0595947189],"iteration":201,"passed_time":2.687467158,"remaining_time":10.6168257},
{"learn":[0.05958690008],"iteration":202,"passed_time":2.699307985,"remaining_time":10.59777569},
{"learn":[0.0595767091],"iteration":203,"passed_time":2.711076442,"remaining_time":10.57851396},
{"learn":[0.05956179602],"iteration":204,"passed_time":2.72463926,"remaining_time":10.56628396},
{"learn":[0.05954572721],"iteration":205,"passed_time":2.73707139,"remaining_time":10.54968293},
{"learn":[0.05953466571],"iteration":206,"passed_time":2.749902956,"remaining_time":10.53465239},
{"learn":[0.05952473692],"iteration":207,"passed_time":2.762098514,"remaining_time":10.51722127},
{"learn":[0.0595155691],"iteration":208,"passed_time":2.775559172,"remaining_time":10.50462825},
{"learn":[0.05950623117],"iteration":209,"passed_time":2.788859171,"remaining_time":10.4914226},
{"learn":[0.05949839237],"iteration":210,"passed_time":2.803070372,"remaining_time":10.48162334},
{"learn":[0.05948811329],"iteration":211,"passed_time":2.816358331,"remaining_time":10.46835078},
{"learn":[0.05948021679],"iteration":212,"passed_time":2.828610928,"remaining_time":10.45125258},
{"learn":[0.0594703217],"iteration":213,"passed_time":2.842207745,"remaining_time":10.43913686},
{"learn":[0.05945865851],"iteration":214,"passed_time":2.855120974,"remaining_time":10.42451146},
{"learn":[0.05945036723],"iteration":215,"passed_time":2.867084419,"remaining_time":10.40645456},
{"learn":[0.0594353625],"iteration":216,"passed_time":2.8816766,"remaining_time":10.39793907},
{"learn":[0.05942771459],"iteration":217,"passed_time":2.895923299,"remaining_time":10.38812853},
{"learn":[0.05942037685],"iteration":218,"passed_time":2.910641348,"remaining_time":10.37995842},
{"learn":[0.0594063374],"iteration":219,"passed_time":2.924217625,"remaining_time":10.36768067},
{"learn":[0.05939589916],"iteration":220,"passed_time":2.936335146,"remaining_time":10.35024922},
{"learn":[0.05938584376],"iteration":221,"passed_time":2.950298193,"remaining_time":10.33933331},
{"learn":[0.05937630085],"iteration":222,"passed_time":2.963283876,"remaining_time":10.32498463},
{"learn":[0.05936682069],"iteration":223,"passed_time":2.97572938,"remaining_time":10.30877678},
{"learn":[0.05935451927],"iteration":224,"passed_time":2.988148801,"remaining_time":10.29251254},
{"learn":[0.05934515103],"iteration":225,"passed_time":3.002758481,"remaining_time":10.28378347},
{"learn":[0.05933449778],"iteration":226,"passed_time":3.015002745,"remaining_time":10.26694767},
{"learn":[0.0593248738],"iteration":227,"passed_time":3.028706598,"remaining_time":10.25509427},
{"learn":[0.05931294899],"iteration":228,"passed_time":3.044088403,"remaining_time":10.24887406},
{"learn":[0.05929966061],"iteration":229,"passed_time":3.057199038,"remaining_time":10.23497069},
{"learn":[0.0592925678],"iteration":230,"passed_time":3.068877957,"remaining_time":10.21630801},
{"learn":[0.05928270867],"iteration":231,"passed_time":3.081139971,"remaining_time":10.19963576},
{"learn":[0.05927421184],"iteration":232,"passed_time":3.09347448,"remaining_time":10.18324003},
{"learn":[0.05926392485],"iteration":233,"passed_time":3.10631842,"remaining_time":10.16854662},
{"learn":[0.05925639965],"iteration":234,"passed_time":3.119053325,"remaining_time":10.15351402},
{"learn":[0.0592497784],"iteration":235,"passed_time":3.133633673,"remaining_time":10.14447511},
{"learn":[0.05923964386],"iteration":236,"passed_time":3.145629784,"remaining_time":10.12706973},
{"learn":[0.0592298161],"iteration":237,"passed_time":3.158515805,"remaining_time":10.11255901},
{"learn":[0.05922243173],"iteration":238,"passed_time":3.171551194,"remaining_time":10.09853748},
{"learn":[0.05921689241],"iteration":239,"passed_time":3.184395635,"remaining_time":10.08391951},
{"learn":[0.05920929095],"iteration":240,"passed_time":3.196583319,"remaining_time":10.06724788},
{"learn":[0.05920259079],"iteration":241,"passed_time":3.21175926,"remaining_time":10.05997322},
{"learn":[0.05919539623],"iteration":242,"passed_time":3.223859907,"remaining_time":10.04305329},
{"learn":[0.05918113805],"iteration":243,"passed_time":3.238136437,"remaining_time":10.03291454},
{"learn":[0.05917071077],"iteration":244,"passed_time":3.251641551,"remaining_time":10.02036478},
{"learn":[0.05916134111],"iteration":245,"passed_time":3.265607807,"remaining_time":10.00922068},
{"learn":[0.05915195379],"iteration":246,"passed_time":3.281636369,"remaining_time":10.00434083},
{"learn":[0.05914465541],"iteration":247,"passed_time":3.2949697,"remaining_time":9.991198446},
{"learn":[0.05913727096],"iteration":248,"passed_time":3.306790654,"remaining_time":9.973493096},
{"learn":[0.05912944909],"iteration":249,"passed_time":3.318854469,"remaining_time":9.956563408},
{"learn":[0.05912172787],"iteration":250,"passed_time":3.331085984,"remaining_time":9.940172917},
{"learn":[0.05911519765],"iteration":251,"passed_time":3.343662522,"remaining_time":9.92483955},
{"learn":[0.05910689758],"iteration":252,"passed_time":3.35524278,"remaining_time":9.90658639},
{"learn":[0.05910094254],"iteration":253,"passed_time":3.368449576,"remaining_time":9.893162929},
{"learn":[0.05909404306],"iteration":254,"passed_time":3.381832655,"remaining_time":9.880256187},
{"learn":[0.0590852494],"iteration":255,"passed_time":3.394768257,"remaining_time":9.866045247},
{"learn":[0.05907331159],"iteration":256,"passed_time":3.407760481,"remaining_time":9.852007929},
{"learn":[0.05906595938],"iteration":257,"passed_time":3.422086593,"remaining_time":9.84181493},
{"learn":[0.05905997911],"iteration":258,"passed_time":3.435413674,"remaining_time":9.828731787},
{"learn":[0.05905010596],"iteration":259,"passed_time":3.448528934,"remaining_time":9.815043889},
{"learn":[0.05904520204],"iteration":260,"passed_time":3.460622873,"remaining_time":9.798468593},
{"learn":[0.05904031029],"iteration":261,"passed_time":3.473634388,"remaining_time":9.78451213},
{"learn":[0.05903353938],"iteration":262,"passed_time":3.485400469,"remaining_time":9.767072797},
{"learn":[0.05902757397],"iteration":263,"passed_time":3.497905303,"remaining_time":9.751735995},
{"learn":[0.05902141465],"iteration":264,"passed_time":3.510195606,"remaining_time":9.735825548},
{"learn":[0.05901594431],"iteration":265,"passed_time":3.522549323,"remaining_time":9.720117304},
{"learn":[0.05900925321],"iteration":266,"passed_time":3.535560754,"remaining_time":9.706239823},
{"learn":[0.05900072545],"iteration":267,"passed_time":3.549095658,"remaining_time":9.693798588},
{"learn":[0.05899193104],"iteration":268,"passed_time":3.561905225,"remaining_time":9.67937814},
{"learn":[0.05898250574],"iteration":269,"passed_time":3.575175685,"remaining_time":9.66621574},
{"learn":[0.05897789705],"iteration":270,"passed_time":3.586054105,"remaining_time":9.646617869},
{"learn":[0.05897241181],"iteration":271,"passed_time":3.598403864,"remaining_time":9.631022105},
{"learn":[0.05896330277],"iteration":272,"passed_time":3.611313342,"remaining_time":9.616940659},
{"learn":[0.0589561787],"iteration":273,"passed_time":3.624415727,"remaining_time":9.603378898},
{"learn":[0.05895030289],"iteration":274,"passed_time":3.636733571,"remaining_time":9.587752142},
{"learn":[0.05894223164],"iteration":275,"passed_time":3.649124786,"remaining_time":9.572341829},
{"learn":[0.05893516263],"iteration":276,"passed_time":3.662002474,"remaining_time":9.558223065},
{"learn":[0.05892827861],"iteration":277,"passed_time":3.675220187,"remaining_time":9.544996312},
{"learn":[0.05892350064],"iteration":278,"passed_time":3.689915862,"remaining_time":9.535589019},
{"learn":[0.05891775469],"iteration":279,"passed_time":3.701449539,"remaining_time":9.5180131},
{"learn":[0.0589131769],"iteration":280,"passed_time":3.713682554,"remaining_time":9.502269594},
{"learn":[0.05891002634],"iteration":281,"passed_time":3.725495591,"remaining_time":9.485481681},
{"learn":[0.05890351287],"iteration":282,"passed_time":3.738985164,"remaining_time":9.472976545},
{"learn":[0.05889692249],"iteration":283,"passed_time":3.751525495,"remaining_time":9.458071319},
{"learn":[0.05889025213],"iteration":284,"passed_time":3.764368353,"remaining_time":9.443941656},
{"learn":[0.05888449288],"iteration":285,"passed_time":3.77669732,"remaining_time":9.428538066},
{"learn":[0.05887715459],"iteration":286,"passed_time":3.788628893,"remaining_time":9.412168644},
{"learn":[0.05887098483],"iteration":287,"passed_time":3.800684834,"remaining_time":9.396137506},
{"learn":[0.05886425357],"iteration":288,"passed_time":3.813951377,"remaining_time":9.383112211},
{"learn":[0.05885924833],"iteration":289,"passed_time":3.826085022,"remaining_time":9.367311605},
{"learn":[0.05885541616],"iteration":290,"passed_time":3.838466279,"remaining_time":9.35213949},
{"learn":[0.05885265841],"iteration":291,"passed_time":3.850137823,"remaining_time":9.335265682},
{"learn":[0.05884770748],"iteration":292,"passed_time":3.862720445,"remaining_time":9.320625783},
{"learn":[0.05884167168],"iteration":293,"passed_time":3.875382978,"remaining_time":9.306191777},
{"learn":[0.05883773403],"iteration":294,"passed_time":3.887940392,"remaining_time":9.291518565},
{"learn":[0.05883311588],"iteration":295,"passed_time":3.900712253,"remaining_time":9.277369684},
{"learn":[0.05882562698],"iteration":296,"passed_time":3.914271947,"remaining_time":9.265094879},
{"learn":[0.05882043529],"iteration":297,"passed_time":3.925425728,"remaining_time":9.247143829},
{"learn":[0.05881403399],"iteration":298,"passed_time":3.938145217,"remaining_time":9.23290902},
{"learn":[0.05880970607],"iteration":299,"passed_time":3.951134525,"remaining_time":9.219313891},
{"learn":[0.05880540903],"iteration":300,"passed_time":3.964444899,"remaining_time":9.206468386},
{"learn":[0.05879855422],"iteration":301,"passed_time":3.977760439,"remaining_time":9.193631743},
{"learn":[0.05878846068],"iteration":302,"passed_time":3.98984742,"remaining_time":9.177965847},
{"learn":[0.05878158477],"iteration":303,"passed_time":4.003352284,"remaining_time":9.165569702},
{"learn":[0.05877771057],"iteration":304,"passed_time":4.015506178,"remaining_time":9.150087847},
{"learn":[0.05877351666],"iteration":305,"passed_time":4.027645114,"remaining_time":9.134593821},
{"learn":[0.05876763893],"iteration":306,"passed_time":4.040131365,"remaining_time":9.119905655},
{"learn":[0.05876230923],"iteration":307,"passed_time":4.052101894,"remaining_time":9.104073086},
{"learn":[0.05875418698],"iteration":308,"passed_time":4.065373728,"remaining_time":9.091175554},
{"learn":[0.05874736083],"iteration":309,"passed_time":4.077723862,"remaining_time":9.07622408},
{"learn":[0.05874356397],"iteration":310,"passed_time":4.090501014,"remaining_time":9.062235366},
{"learn":[0.05873910297],"iteration":311,"passed_time":4.103442408,"remaining_time":9.048616592},
{"learn":[0.05873273574],"iteration":312,"passed_time":4.117014435,"remaining_time":9.036386315},
{"learn":[0.05872746453],"iteration":313,"passed_time":4.130376098,"remaining_time":9.023687908},
{"learn":[0.05872054487],"iteration":314,"passed_time":4.142551324,"remaining_time":9.00840526},
{"learn":[0.05871501743],"iteration":315,"passed_time":4.156297925,"remaining_time":8.996543609},
{"learn":[0.05870963647],"iteration":316,"passed_time":4.168711096,"remaining_time":8.981797094},
{"learn":[0.05870533812],"iteration":317,"passed_time":4.181584827,"remaining_time":8.968052994},
{"learn":[0.05870056698],"iteration":318,"passed_time":4.195741406,"remaining_time":8.95705297},
{"learn":[0.05869697411],"iteration":319,"passed_time":4.207663479,"remaining_time":8.941284893},
{"learn":[0.05869364165],"iteration":320,"passed_time":4.220330971,"remaining_time":8.927117536},
{"learn":[0.05868747416],"iteration":321,"passed_time":4.233926413,"remaining_time":8.914913378},
{"learn":[0.05868360898],"iteration":322,"passed_time":4.244982324,"remaining_time":8.897377811},
{"learn":[0.05867853412],"iteration":323,"passed_time":4.258927747,"remaining_time":8.885910978},
{"learn":[0.0586724755],"iteration":324,"passed_time":4.271268631,"remaining_time":8.871096388},
{"learn":[0.05866632753],"iteration":325,"passed_time":4.284662042,"remaining_time":8.858473057},
{"learn":[0.05866261569],"iteration":326,"passed_time":4.297172042,"remaining_time":8.844026864},
{"learn":[0.05865801996],"iteration":327,"passed_time":4.309269148,"remaining_time":8.828746546},
{"learn":[0.05865203727],"iteration":328,"passed_time":4.321432375,"remaining_time":8.813620436},
{"learn":[0.058646706],"iteration":329,"passed_time":4.334110949,"remaining_time":8.799558593},
{"learn":[0.05864208284],"iteration":330,"passed_time":4.346539203,"remaining_time":8.784999175},
{"learn":[0.0586369221],"iteration":331,"passed_time":4.358727554,"remaining_time":8.769969897},
{"learn":[0.05862979857],"iteration":332,"passed_time":4.369990828,"remaining_time":8.753104753},
{"learn":[0.05862150791],"iteration":333,"passed_time":4.382683944,"remaining_time":8.739124271},
{"learn":[0.05861428546],"iteration":334,"passed_time":4.395528759,"remaining_time":8.725452612},
{"learn":[0.05860856863],"iteration":335,"passed_time":4.408820634,"remaining_time":8.712669349},
{"learn":[0.05860323279],"iteration":336,"passed_time":4.421184559,"remaining_time":8.698057455},
{"learn":[0.05859764947],"iteration":337,"passed_time":4.435495296,"remaining_time":8.687271852},
{"learn":[0.05859360576],"iteration":338,"passed_time":4.447721811,"remaining_time":8.672401526},
{"learn":[0.05858697803],"iteration":339,"passed_time":4.461569282,"remaining_time":8.660693311},
{"learn":[0.05857940362],"iteration":340,"passed_time":4.475234345,"remaining_time":8.648620039},
{"learn":[0.05857588625],"iteration":341,"passed_time":4.494681725,"remaining_time":8.647662501},
{"learn":[0.05856850176],"iteration":342,"passed_time":4.511312964,"remaining_time":8.641202966},
{"learn":[0.05856373988],"iteration":343,"passed_time":4.526475781,"remaining_time":8.631884047},
{"learn":[0.05855953038],"iteration":344,"passed_time":4.54126166,"remaining_time":8.621815615},
{"learn":[0.05855534198],"iteration":345,"passed_time":4.555220624,"remaining_time":8.610156902},
{"learn":[0.05854965514],"iteration":346,"passed_time":4.569193129,"remaining_time":8.598510414},
{"learn":[0.05854543919],"iteration":347,"passed_time":4.582932897,"remaining_time":8.586414509},
{"learn":[0.05853886463],"iteration":348,"passed_time":4.596123861,"remaining_time":8.573285483},
{"learn":[0.05853371316],"iteration":349,"passed_time":4.608671817,"remaining_time":8.558961946},
{"learn":[0.05852693056],"iteration":350,"passed_time":4.621018034,"remaining_time":8.544275511},
{"learn":[0.05852209584],"iteration":351,"passed_time":4.633352127,"remaining_time":8.529580052},
{"learn":[0.05851812194],"iteration":352,"passed_time":4.646313561,"remaining_time":8.516047802},
{"learn":[0.05851229989],"iteration":353,"passed_time":4.659383615,"remaining_time":8.502716992},
{"learn":[0.05850573177],"iteration":354,"passed_time":4.678193779,"remaining_time":8.499816866},
{"learn":[0.05850078741],"iteration":355,"passed_time":4.693227478,"remaining_time":8.489995775},
{"learn":[0.05849712199],"iteration":356,"passed_time":4.707267063,"remaining_time":8.478354962},
{"learn":[0.05848946748],"iteration":357,"passed_time":4.72042807,"remaining_time":8.465125198},
{"learn":[0.05848470084],"iteration":358,"passed_time":4.73465177,"remaining_time":8.453793273},
{"learn":[0.05847956463],"iteration":359,"passed_time":4.748193382,"remaining_time":8.441232679},
{"learn":[0.05847378715],"iteration":360,"passed_time":4.762562908,"remaining_time":8.430132128},
{"learn":[0.05846957803],"iteration":361,"passed_time":4.775603338,"remaining_time":8.416671077},
{"learn":[0.05846547837],"iteration":362,"passed_time":4.788651018,"remaining_time":8.403225064},
{"learn":[0.0584608981],"iteration":363,"passed_time":4.802484072,"remaining_time":8.391153489},
{"learn":[0.05845716725],"iteration":364,"passed_time":4.814760126,"remaining_time":8.376363508},
{"learn":[0.05845501184],"iteration":365,"passed_time":4.827354414,"remaining_time":8.36213852},
{"learn":[0.05844986722],"iteration":366,"passed_time":4.842342781,"remaining_time":8.352051718},
{"learn":[0.05844435538],"iteration":367,"passed_time":4.854547673,"remaining_time":8.33715796},
{"learn":[0.05843523246],"iteration":368,"passed_time":4.866151471,"remaining_time":8.32125089},
{"learn":[0.05843183013],"iteration":369,"passed_time":4.879386682,"remaining_time":8.308144892},
{"learn":[0.05842915331],"iteration":370,"passed_time":4.895903136,"remaining_time":8.300601273},
{"learn":[0.05842357617],"iteration":371,"passed_time":4.931235878,"remaining_time":8.324774546},
{"learn":[0.05841822612],"iteration":372,"passed_time":4.9448909,"remaining_time":8.312189261},
{"learn":[0.0584172342],"iteration":373,"passed_time":4.95590248,"remaining_time":8.295173669},
{"learn":[0.05841278852],"iteration":374,"passed_time":4.969806947,"remaining_time":8.283011579},
{"learn":[0.05840720713],"iteration":375,"passed_time":4.983808826,"remaining_time":8.271001881},
{"learn":[0.05840231227],"iteration":376,"passed_time":4.998080732,"remaining_time":8.259427841},
{"learn":[0.05839853951],"iteration":377,"passed_time":5.011741296,"remaining_time":8.246833561},
{"learn":[0.05838919947],"iteration":378,"passed_time":5.024567321,"remaining_time":8.232866243},
{"learn":[0.05837988802],"iteration":379,"passed_time":5.039137752,"remaining_time":8.22175107},
{"learn":[0.05837558408],"iteration":380,"passed_time":5.052966016,"remaining_time":8.209411978},
{"learn":[0.05837107712],"iteration":381,"passed_time":5.06799059,"remaining_time":8.199000483},
{"learn":[0.05836676197],"iteration":382,"passed_time":5.081908515,"remaining_time":8.186782124},
{"learn":[0.05836123363],"iteration":383,"passed_time":5.094508635,"remaining_time":8.172440935},
{"learn":[0.05835567585],"iteration":384,"passed_time":5.108329399,"remaining_time":8.16005865},
{"learn":[0.05835111146],"iteration":385,"passed_time":5.125503817,"remaining_time":8.15300348},
{"learn":[0.05834912161],"iteration":386,"passed_time":5.140190826,"remaining_time":8.141956011},
{"learn":[0.05834440879],"iteration":387,"passed_time":5.155564173,"remaining_time":8.131972355},
{"learn":[0.05834079486],"iteration":388,"passed_time":5.170597705,"remaining_time":8.121427244},
{"learn":[0.05833802305],"iteration":389,"passed_time":5.18476795,"remaining_time":8.109508845},
{"learn":[0.05833423142],"iteration":390,"passed_time":5.199439793,"remaining_time":8.098360189},
{"learn":[0.05832973728],"iteration":391,"passed_time":5.213551041,"remaining_time":8.086324064},
{"learn":[0.05832476497],"iteration":392,"passed_time":5.227611584,"remaining_time":8.074199062},
{"learn":[0.05832163137],"iteration":393,"passed_time":5.243854385,"remaining_time":8.065420703},
{"learn":[0.05831679889],"iteration":394,"passed_time":5.257401454,"remaining_time":8.052475645},
{"learn":[0.05831510104],"iteration":395,"passed_time":5.276753923,"remaining_time":8.048382246},
{"learn":[0.05831145411],"iteration":396,"passed_time":5.292074023,"remaining_time":8.038087245},
{"learn":[0.058307775],"iteration":397,"passed_time":5.308481816,"remaining_time":8.029412193},
{"learn":[0.05830556109],"iteration":398,"passed_time":5.322389533,"remaining_time":8.016932605},
{"learn":[0.05830265694],"iteration":399,"passed_time":5.335884689,"remaining_time":8.003827033},
{"learn":[0.05829898411],"iteration":400,"passed_time":5.34965133,"remaining_time":7.991125054},
{"learn":[0.05829511655],"iteration":401,"passed_time":5.364029022,"remaining_time":7.979326754},
{"learn":[0.05829151662],"iteration":402,"passed_time":5.377546718,"remaining_time":7.966241665},
{"learn":[0.05828584158],"iteration":403,"passed_time":5.392756575,"remaining_time":7.955650788},
{"learn":[0.05828181309],"iteration":404,"passed_time":5.407489039,"remaining_time":7.944335749},
{"learn":[0.05827821007],"iteration":405,"passed_time":5.421333302,"remaining_time":7.931704387},
{"learn":[0.05827569626],"iteration":406,"passed_time":5.434752503,"remaining_time":7.91844775},
{"learn":[0.05827164071],"iteration":407,"passed_time":5.449422305,"remaining_time":7.907004913},
{"learn":[0.05826715195],"iteration":408,"passed_time":5.464617912,"remaining_time":7.896306078},
{"learn":[0.05826101801],"iteration":409,"passed_time":5.478836154,"remaining_time":7.884178856},
{"learn":[0.05825846444],"iteration":410,"passed_time":5.493497373,"remaining_time":7.872676283},
{"learn":[0.05825320639],"iteration":411,"passed_time":5.50655001,"remaining_time":7.858862636},
{"learn":[0.05824735392],"iteration":412,"passed_time":5.520221574,"remaining_time":7.845932358},
{"learn":[0.05824544965],"iteration":413,"passed_time":5.53276703,"remaining_time":7.83140454},
{"learn":[0.05824130317],"iteration":414,"passed_time":5.54577467,"remaining_time":7.817537788},
{"learn":[0.05823749172],"iteration":415,"passed_time":5.557510545,"remaining_time":7.801889803},
{"learn":[0.05823326267],"iteration":416,"passed_time":5.570366443,"remaining_time":7.787826466},
{"learn":[0.05822613157],"iteration":417,"passed_time":5.583911013,"remaining_time":7.774727774},
{"learn":[0.05822399929],"iteration":418,"passed_time":5.596191817,"remaining_time":7.759874572},
{"learn":[0.05822080738],"iteration":419,"passed_time":5.608519576,"remaining_time":7.745098463},
{"learn":[0.05821734891],"iteration":420,"passed_time":5.623498028,"remaining_time":7.733979473},
{"learn":[0.05821509621],"iteration":421,"passed_time":5.638067043,"remaining_time":7.722281401},
{"learn":[0.0582074458],"iteration":422,"passed_time":5.65239803,"remaining_time":7.710245067},
{"learn":[0.05820376321],"iteration":423,"passed_time":5.666482113,"remaining_time":7.697862492},
{"learn":[0.05820015368],"iteration":424,"passed_time":5.679849317,"remaining_time":7.684502017},
{"learn":[0.05819415098],"iteration":425,"passed_time":5.69296041,"remaining_time":7.670796421},
{"learn":[0.05819199353],"iteration":426,"passed_time":5.704482546,"remaining_time":7.654961355},
{"learn":[0.05818876551],"iteration":427,"passed_time":5.71925955,"remaining_time":7.643496408},
{"learn":[0.05818692693],"iteration":428,"passed_time":5.733251638,"remaining_time":7.630971294},
{"learn":[0.05818455272],"iteration":429,"passed_time":5.74727639,"remaining_time":7.618482657},
{"learn":[0.05818004049],"iteration":430,"passed_time":5.761171358,"remaining_time":7.605815552},
{"learn":[0.05817653345],"iteration":431,"passed_time":5.774816881,"remaining_time":7.592814788},
{"learn":[0.05817466346],"iteration":432,"passed_time":5.789743211,"remaining_time":7.581488223},
{"learn":[0.05817152733],"iteration":433,"passed_time":5.805488621,"remaining_time":7.571213271},
{"learn":[0.05816465456],"iteration":434,"passed_time":5.819444669,"remaining_time":7.558589053},
{"learn":[0.05816109251],"iteration":435,"passed_time":5.833088734,"remaining_time":7.545555151},
{"learn":[0.05815745542],"iteration":436,"passed_time":5.850087036,"remaining_time":7.53683982},
{"learn":[0.05815420203],"iteration":437,"passed_time":5.865804532,"remaining_time":7.526443258},
{"learn":[0.05815056174],"iteration":438,"passed_time":5.880110478,"remaining_time":7.514218629},
{"learn":[0.05814364621],"iteration":439,"passed_time":5.893789707,"remaining_time":7.5011869},
{"learn":[0.05813953924],"iteration":440,"passed_time":5.908358389,"remaining_time":7.489279682},
{"learn":[0.05813282118],"iteration":441,"passed_time":5.922021536,"remaining_time":7.476217234},
{"learn":[0.05813096173],"iteration":442,"passed_time":5.935601229,"remaining_time":7.463047144},
{"learn":[0.05812720862],"iteration":443,"passed_time":5.949484114,"remaining_time":7.450254882},
{"learn":[0.05812221938],"iteration":444,"passed_time":5.963441162,"remaining_time":7.437550214},
{"learn":[0.05812010099],"iteration":445,"passed_time":5.975608806,"remaining_time":7.422617216},
{"learn":[0.05811498191],"iteration":446,"passed_time":5.989835172,"remaining_time":7.410243513},
{"learn":[0.05811092741],"iteration":447,"passed_time":6.002124476,"remaining_time":7.395474801},
{"learn":[0.05810843175],"iteration":448,"passed_time":6.016058817,"remaining_time":7.382735875},
{"learn":[0.05810607447],"iteration":449,"passed_time":6.02834512,"remaining_time":7.367977369},
{"learn":[0.05810329792],"iteration":450,"passed_time":6.039468361,"remaining_time":7.351814036},
{"learn":[0.05809974444],"iteration":451,"passed_time":6.054317236,"remaining_time":7.340189924},
{"learn":[0.05809674281],"iteration":452,"passed_time":6.065950033,"remaining_time":7.324668141},
{"learn":[0.05809263916],"iteration":453,"passed_time":6.078707353,"remaining_time":7.310515892},
{"learn":[0.05809049149],"iteration":454,"passed_time":6.092557657,"remaining_time":7.297678951},
{"learn":[0.05808751642],"iteration":455,"passed_time":6.106484748,"remaining_time":7.284929173},
{"learn":[0.05808346407],"iteration":456,"passed_time":6.121054055,"remaining_time":7.272937312},
{"learn":[0.05808071571],"iteration":457,"passed_time":6.134448383,"remaining_time":7.259543719},
{"learn":[0.05807596884],"iteration":458,"passed_time":6.148215482,"remaining_time":7.24658949},
{"learn":[0.05807304822],"iteration":459,"passed_time":6.162787456,"remaining_time":7.234576578},
{"learn":[0.05806731097],"iteration":460,"passed_time":6.176445686,"remaining_time":7.221484219},
{"learn":[0.0580613857],"iteration":461,"passed_time":6.189655899,"remaining_time":7.207867692},
{"learn":[0.05805768508],"iteration":462,"passed_time":6.204832507,"remaining_time":7.196533599},
{"learn":[0.05805585574],"iteration":463,"passed_time":6.215846587,"remaining_time":7.180374505},
{"learn":[0.05805258989],"iteration":464,"passed_time":6.228448082,"remaining_time":7.166063922},
{"learn":[0.05805008134],"iteration":465,"passed_time":6.240109669,"remaining_time":7.150683612},
{"learn":[0.05804594944],"iteration":466,"passed_time":6.251817545,"remaining_time":7.135372058},
{"learn":[0.05804391242],"iteration":467,"passed_time":6.264752522,"remaining_time":7.121470816},
{"learn":[0.05803847459],"iteration":468,"passed_time":6.278042647,"remaining_time":7.10797579},
{"learn":[0.05803464224],"iteration":469,"passed_time":6.289717775,"remaining_time":7.09266047},
{"learn":[0.05803301539],"iteration":470,"passed_time":6.301835629,"remaining_time":7.077857851},
{"learn":[0.05802808024],"iteration":471,"passed_time":6.314296423,"remaining_time":7.063450236},
{"learn":[0.05802307177],"iteration":472,"passed_time":6.32840663,"remaining_time":7.050888571},
{"learn":[0.05801984376],"iteration":473,"passed_time":6.341137035,"remaining_time":7.036789199},
{"learn":[0.05801395851],"iteration":474,"passed_time":6.353628994,"remaining_time":7.022432046},
{"learn":[0.05801340307],"iteration":475,"passed_time":6.364945641,"remaining_time":7.006788899},
{"learn":[0.0580109248],"iteration":476,"passed_time":6.378910438,"remaining_time":6.99406742},
{"learn":[0.05800678236],"iteration":477,"passed_time":6.393743231,"remaining_time":6.982288633},
{"learn":[0.05800165293],"iteration":478,"passed_time":6.407023607,"remaining_time":6.968808558},
{"learn":[0.05799793648],"iteration":479,"passed_time":6.419808634,"remaining_time":6.954792687},
{"learn":[0.05799318923],"iteration":480,"passed_time":6.433837303,"remaining_time":6.942123826},
{"learn":[0.05799078541],"iteration":481,"passed_time":6.446215018,"remaining_time":6.927675061},
{"learn":[0.0579871001],"iteration":482,"passed_time":6.459107498,"remaining_time":6.913785873},
{"learn":[0.05798173441],"iteration":483,"passed_time":6.471077652,"remaining_time":6.898917496},
{"learn":[0.05797811212],"iteration":484,"passed_time":6.485580462,"remaining_time":6.886750388},
{"learn":[0.05797648863],"iteration":485,"passed_time":6.498887628,"remaining_time":6.873309137},
{"learn":[0.05797237773],"iteration":486,"passed_time":6.511784232,"remaining_time":6.859435957},
{"learn":[0.05796961573],"iteration":487,"passed_time":6.524740709,"remaining_time":6.845629596},
{"learn":[0.05796691755],"iteration":488,"passed_time":6.540545533,"remaining_time":6.834803205},
{"learn":[0.05796368454],"iteration":489,"passed_time":6.554698237,"remaining_time":6.822236941},
{"learn":[0.05795952152],"iteration":490,"passed_time":6.566620769,"remaining_time":6.807352283},
{"learn":[0.05795782367],"iteration":491,"passed_time":6.578309521,"remaining_time":6.792238286},
{"learn":[0.05795496423],"iteration":492,"passed_time":6.591625311,"remaining_time":6.778811425},
{"learn":[0.05795121621],"iteration":493,"passed_time":6.60502543,"remaining_time":6.765471392},
{"learn":[0.0579474755],"iteration":494,"passed_time":6.61773092,"remaining_time":6.751422454},
{"learn":[0.05794429778],"iteration":495,"passed_time":6.633208095,"remaining_time":6.740195322},
{"learn":[0.05794099041],"iteration":496,"passed_time":6.645708429,"remaining_time":6.725938309},
{"learn":[0.05793799334],"iteration":497,"passed_time":6.658671405,"remaining_time":6.712154709},
{"learn":[0.05793572334],"iteration":498,"passed_time":6.669630487,"remaining_time":6.696362473},
{"learn":[0.05793103864],"iteration":499,"passed_time":6.681187205,"remaining_time":6.681187205},
{"learn":[0.05792669991],"iteration":500,"passed_time":6.694142598,"remaining_time":6.667419474},
{"learn":[0.05792261719],"iteration":501,"passed_time":6.706170123,"remaining_time":6.652734505},
{"learn":[0.05791732602],"iteration":502,"passed_time":6.718808492,"remaining_time":6.638663659},
{"learn":[0.05791379494],"iteration":503,"passed_time":6.7316231,"remaining_time":6.62477194},
{"learn":[0.05791143372],"iteration":504,"passed_time":6.742720092,"remaining_time":6.609200883},
{"learn":[0.05790891019],"iteration":505,"passed_time":6.754481507,"remaining_time":6.594296175},
{"learn":[0.05790667186],"iteration":506,"passed_time":6.766213465,"remaining_time":6.579375224},
{"learn":[0.05790175687],"iteration":507,"passed_time":6.778179536,"remaining_time":6.564693566},
{"learn":[0.0578990466],"iteration":508,"passed_time":6.790925607,"remaining_time":6.550774996},
{"learn":[0.05789370047],"iteration":509,"passed_time":6.804318685,"remaining_time":6.537482658},
{"learn":[0.05789174688],"iteration":510,"passed_time":6.817594977,"remaining_time":6.524078168},
{"learn":[0.05788661119],"iteration":511,"passed_time":6.830094769,"remaining_time":6.509934077},
{"learn":[0.05788382379],"iteration":512,"passed_time":6.842083297,"remaining_time":6.495311044},
{"learn":[0.05787685063],"iteration":513,"passed_time":6.855781067,"remaining_time":6.482314394},
{"learn":[0.05787353214],"iteration":514,"passed_time":6.868831747,"remaining_time":6.468705626},
{"learn":[0.05787049464],"iteration":515,"passed_time":6.881571901,"remaining_time":6.454807752},
{"learn":[0.05786732999],"iteration":516,"passed_time":6.894175188,"remaining_time":6.440786491},
{"learn":[0.05786577799],"iteration":517,"passed_time":6.905542082,"remaining_time":6.425620239},
{"learn":[0.05785923491],"iteration":518,"passed_time":6.919524462,"remaining_time":6.412892613},
{"learn":[0.05785570023],"iteration":519,"passed_time":6.932726175,"remaining_time":6.399439546},
{"learn":[0.05785220281],"iteration":520,"passed_time":6.945592864,"remaining_time":6.385679428},
{"learn":[0.05785080228],"iteration":521,"passed_time":6.957680512,"remaining_time":6.371209358},
{"learn":[0.05784744977],"iteration":522,"passed_time":6.971953251,"remaining_time":6.358741302},
{"learn":[0.05784219058],"iteration":523,"passed_time":6.984244346,"remaining_time":6.344466238},
{"learn":[0.05783750258],"iteration":524,"passed_time":6.997726128,"remaining_time":6.331276021},
{"learn":[0.05783469896],"iteration":525,"passed_time":7.009880772,"remaining_time":6.316888756},
{"learn":[0.05783188305],"iteration":526,"passed_time":7.022529306,"remaining_time":6.302953248},
{"learn":[0.05782710424],"iteration":527,"passed_time":7.034920937,"remaining_time":6.288792959},
{"learn":[0.05782295821],"iteration":528,"passed_time":7.046391785,"remaining_time":6.273819528},
{"learn":[0.05781889555],"iteration":529,"passed_time":7.057944377,"remaining_time":6.258931806},
{"learn":[0.05781432129],"iteration":530,"passed_time":7.070686698,"remaining_time":6.24510746},
{"learn":[0.05781212709],"iteration":531,"passed_time":7.083190323,"remaining_time":6.231077202},
{"learn":[0.05780695321],"iteration":532,"passed_time":7.096313124,"remaining_time":6.217595176},
{"learn":[0.05780455488],"iteration":533,"passed_time":7.110328836,"remaining_time":6.204893703},
{"learn":[0.05780222804],"iteration":534,"passed_time":7.122601015,"remaining_time":6.19067191},
{"learn":[0.05779860384],"iteration":535,"passed_time":7.135619613,"remaining_time":6.177103545},
{"learn":[0.05779496321],"iteration":536,"passed_time":7.148848825,"remaining_time":6.163718819},
{"learn":[0.05779038621],"iteration":537,"passed_time":7.161311744,"remaining_time":6.149676627},
{"learn":[0.05778850278],"iteration":538,"passed_time":7.172895918,"remaining_time":6.134888717},
{"learn":[0.05778691698],"iteration":539,"passed_time":7.185749275,"remaining_time":6.121193827},
{"learn":[0.05778498411],"iteration":540,"passed_time":7.200173298,"remaining_time":6.108834646},
{"learn":[0.05778023697],"iteration":541,"passed_time":7.212195074,"remaining_time":6.094437904},
{"learn":[0.05777601798],"iteration":542,"passed_time":7.225292876,"remaining_time":6.080955514},
{"learn":[0.05777342137],"iteration":543,"passed_time":7.238292225,"remaining_time":6.067392012},
{"learn":[0.05776850507],"iteration":544,"passed_time":7.251617098,"remaining_time":6.054102348},
{"learn":[0.05776670582],"iteration":545,"passed_time":7.267299929,"remaining_time":6.042773201},
{"learn":[0.05775942099],"iteration":546,"passed_time":7.28147209,"remaining_time":6.030177069},
{"learn":[0.05775610197],"iteration":547,"passed_time":7.293361998,"remaining_time":6.015692743},
{"learn":[0.05775480074],"iteration":548,"passed_time":7.304972421,"remaining_time":6.000988273},
{"learn":[0.05775157471],"iteration":549,"passed_time":7.318531865,"remaining_time":5.987889708},
{"learn":[0.05774905405],"iteration":550,"passed_time":7.332138099,"remaining_time":5.974827598},
{"learn":[0.05774441771],"iteration":551,"passed_time":7.344599809,"remaining_time":5.960834628},
{"learn":[0.05774014757],"iteration":552,"passed_time":7.35856719,"remaining_time":5.948064257},
{"learn":[0.05773726042],"iteration":553,"passed_time":7.374585836,"remaining_time":5.936940944},
{"learn":[0.05773426987],"iteration":554,"passed_time":7.386760771,"remaining_time":5.922718096},
{"learn":[0.05773220292],"iteration":555,"passed_time":7.399271688,"remaining_time":5.908770916},
{"learn":[0.05772722425],"iteration":556,"passed_time":7.411517785,"remaining_time":5.894618274},
{"learn":[0.0577245844],"iteration":557,"passed_time":7.424016327,"remaining_time":5.880672431},
{"learn":[0.05772203499],"iteration":558,"passed_time":7.436603865,"remaining_time":5.866801976},
{"learn":[0.05771906528],"iteration":559,"passed_time":7.450678031,"remaining_time":5.854104168},
{"learn":[0.0577132439],"iteration":560,"passed_time":7.466484314,"remaining_time":5.842756888},
{"learn":[0.05771109716],"iteration":561,"passed_time":7.479151556,"remaining_time":5.828947298},
{"learn":[0.05770893426],"iteration":562,"passed_time":7.491256452,"remaining_time":5.814705275},
{"learn":[0.05770462381],"iteration":563,"passed_time":7.503389431,"remaining_time":5.800492539},
{"learn":[0.0577033687],"iteration":564,"passed_time":7.514768824,"remaining_time":5.785706971},
{"learn":[0.05769931211],"iteration":565,"passed_time":7.526031724,"remaining_time":5.770844114},
{"learn":[0.05769536416],"iteration":566,"passed_time":7.537671896,"remaining_time":5.756282065},
{"learn":[0.05769254245],"iteration":567,"passed_time":7.550522044,"remaining_time":5.742650569},
{"learn":[0.05768602494],"iteration":568,"passed_time":7.564845572,"remaining_time":5.730137859},
{"learn":[0.05768467929],"iteration":569,"passed_time":7.576104139,"remaining_time":5.715306631},
{"learn":[0.05768070835],"iteration":570,"passed_time":7.589795451,"remaining_time":5.702315672},
{"learn":[0.05767656771],"iteration":571,"passed_time":7.603848702,"remaining_time":5.689593085},
{"learn":[0.05767097474],"iteration":572,"passed_time":7.615436793,"remaining_time":5.675028814},
{"learn":[0.05766891267],"iteration":573,"passed_time":7.628101201,"remaining_time":5.661273714},
{"learn":[0.05766595056],"iteration":574,"passed_time":7.639451347,"remaining_time":5.646550995},
{"learn":[0.05766271602],"iteration":575,"passed_time":7.651154306,"remaining_time":5.632099698},
{"learn":[0.05766042195],"iteration":576,"passed_time":7.66460059,"remaining_time":5.618935961},
{"learn":[0.05765801441],"iteration":577,"passed_time":7.677364243,"remaining_time":5.605272856},
{"learn":[0.05765639451],"iteration":578,"passed_time":7.689507137,"remaining_time":5.591161494},
{"learn":[0.05765360044],"iteration":579,"passed_time":7.700237816,"remaining_time":5.57603428},
{"learn":[0.0576499336],"iteration":580,"passed_time":7.714143116,"remaining_time":5.563211645},
{"learn":[0.05764811374],"iteration":581,"passed_time":7.727222461,"remaining_time":5.549792077},
{"learn":[0.05764520909],"iteration":582,"passed_time":7.740001988,"remaining_time":5.536159227},
{"learn":[0.05764400332],"iteration":583,"passed_time":7.754791575,"remaining_time":5.523961122},
{"learn":[0.05763796],"iteration":584,"passed_time":7.766403331,"remaining_time":5.509499799},
{"learn":[0.05763485685],"iteration":585,"passed_time":7.777589693,"remaining_time":5.494747667},
{"learn":[0.05763098972],"iteration":586,"passed_time":7.789924036,"remaining_time":5.480815378},
{"learn":[0.0576275498],"iteration":587,"passed_time":7.801445506,"remaining_time":5.46631896},
{"learn":[0.0576250729],"iteration":588,"passed_time":7.816451831,"remaining_time":5.454264351},
{"learn":[0.05762320175],"iteration":589,"passed_time":7.828359863,"remaining_time":5.440046684},
{"learn":[0.05762022757],"iteration":590,"passed_time":7.840718788,"remaining_time":5.426148873},
{"learn":[0.05761716858],"iteration":591,"passed_time":7.853673931,"remaining_time":5.412667168},
{"learn":[0.05761358442],"iteration":592,"passed_time":7.86541068,"remaining_time":5.398351006},
{"learn":[0.05761290277],"iteration":593,"passed_time":7.878246954,"remaining_time":5.384795056},
{"learn":[0.05761034065],"iteration":594,"passed_time":7.890106781,"remaining_time":5.370576884},
{"learn":[0.05760724247],"iteration":595,"passed_time":7.901827156,"remaining_time":5.356272099},
{"learn":[0.05760354665],"iteration":596,"passed_time":7.913699482,"remaining_time":5.342078545},
{"learn":[0.05760079318],"iteration":597,"passed_time":7.92477385,"remaining_time":5.327356334},
{"learn":[0.05759899956],"iteration":598,"passed_time":7.936550764,"remaining_time":5.313116622},
{"learn":[0.05759580732],"iteration":599,"passed_time":7.948578165,"remaining_time":5.29905211},
{"learn":[0.05759428873],"iteration":600,"passed_time":7.959881312,"remaining_time":5.28451355},
{"learn":[0.0575905463],"iteration":601,"passed_time":7.972173282,"remaining_time":5.270639479},
{"learn":[0.05758727902],"iteration":602,"passed_time":7.984952476,"remaining_time":5.257091431},
{"learn":[0.05758155909],"iteration":603,"passed_time":7.998645038,"remaining_time":5.24414476},
{"learn":[0.05758031487],"iteration":604,"passed_time":8.009260514,"remaining_time":5.229186617},
{"learn":[0.05757417965],"iteration":605,"passed_time":8.021783389,"remaining_time":5.215482929},
{"learn":[0.05757126234],"iteration":606,"passed_time":8.035451868,"remaining_time":5.202524851},
{"learn":[0.05756867067],"iteration":607,"passed_time":8.047729298,"remaining_time":5.188667573},
{"learn":[0.05756605464],"iteration":608,"passed_time":8.060533948,"remaining_time":5.17515398},
{"learn":[0.05756347185],"iteration":609,"passed_time":8.074088934,"remaining_time":5.162122434},
{"learn":[0.05756200367],"iteration":610,"passed_time":8.08580031,"remaining_time":5.147915419},
{"learn":[0.05755828803],"iteration":611,"passed_time":8.098479885,"remaining_time":5.134330384},
{"learn":[0.05755463857],"iteration":612,"passed_time":8.110882724,"remaining_time":5.120573596},
{"learn":[0.05754865051],"iteration":613,"passed_time":8.123244273,"remaining_time":5.10679526},
{"learn":[0.0575470713],"iteration":614,"passed_time":8.13632266,"remaining_time":5.093470283},
{"learn":[0.05754187348],"iteration":615,"passed_time":8.14828623,"remaining_time":5.079451157},
{"learn":[0.05753918141],"iteration":616,"passed_time":8.159550588,"remaining_time":5.06500466},
{"learn":[0.0575357989],"iteration":617,"passed_time":8.171097057,"remaining_time":5.050742841},
{"learn":[0.05753344372],"iteration":618,"passed_time":8.185843687,"remaining_time":5.038459523},
{"learn":[0.05753117078],"iteration":619,"passed_time":8.199917687,"remaining_time":5.025756002},
{"learn":[0.05752737314],"iteration":620,"passed_time":8.21163148,"remaining_time":5.011607618},
{"learn":[0.05752379583],"iteration":621,"passed_time":8.226401484,"remaining_time":4.999324375},
{"learn":[0.05752054976],"iteration":622,"passed_time":8.240440444,"remaining_time":4.986590767},
{"learn":[0.05751859454],"iteration":623,"passed_time":8.251676304,"remaining_time":4.972163927},
{"learn":[0.05751651905],"iteration":624,"passed_time":8.26523454,"remaining_time":4.959140724},
{"learn":[0.05751376789],"iteration":625,"passed_time":8.27818135,"remaining_time":4.945750519},
{"learn":[0.05750864742],"iteration":626,"passed_time":8.290675684,"remaining_time":4.932092552},
{"learn":[0.05750664447],"iteration":627,"passed_time":8.303840483,"remaining_time":4.918835445},
{"learn":[0.05750358274],"iteration":628,"passed_time":8.31612162,"remaining_time":4.905057426},
{"learn":[0.05749952242],"iteration":629,"passed_time":8.327781498,"remaining_time":4.890919293},
{"learn":[0.05749593929],"iteration":630,"passed_time":8.340558401,"remaining_time":4.877442234},
{"learn":[0.05749335495],"iteration":631,"passed_time":8.354382289,"remaining_time":4.864577029},
{"learn":[0.05748862257],"iteration":632,"passed_time":8.3660595,"remaining_time":4.850464197},
{"learn":[0.05748659097],"iteration":633,"passed_time":8.378888317,"remaining_time":4.837023855},
{"learn":[0.05748487068],"iteration":634,"passed_time":8.391314238,"remaining_time":4.823353853},
{"learn":[0.05748102128],"iteration":635,"passed_time":8.403701619,"remaining_time":4.809665707},
{"learn":[0.05747753504],"iteration":636,"passed_time":8.418011607,"remaining_time":4.797077258},
{"learn":[0.05747500114],"iteration":637,"passed_time":8.431009039,"remaining_time":4.783738671},
{"learn":[0.05747121473],"iteration":638,"passed_time":8.444208544,"remaining_time":4.770515312},
{"learn":[0.05746891863],"iteration":639,"passed_time":8.456816664,"remaining_time":4.756959373},
{"learn":[0.05746545288],"iteration":640,"passed_time":8.469801763,"remaining_time":4.743617524},
{"learn":[0.05746313852],"iteration":641,"passed_time":8.483042224,"remaining_time":4.730419184},
{"learn":[0.05746041103],"iteration":642,"passed_time":8.494299874,"remaining_time":4.716119837},
{"learn":[0.05745772261],"iteration":643,"passed_time":8.507509296,"remaining_time":4.702908865},
{"learn":[0.05745562299],"iteration":644,"passed_time":8.519611234,"remaining_time":4.689088354},
{"learn":[0.05745225119],"iteration":645,"passed_time":8.532552211,"remaining_time":4.675732945},
{"learn":[0.05745090025],"iteration":646,"passed_time":8.544581945,"remaining_time":4.661881648},
{"learn":[0.05744668801],"iteration":647,"passed_time":8.558301464,"remaining_time":4.648953882},
{"learn":[0.05744136016],"iteration":648,"passed_time":8.571174028,"remaining_time":4.635565614},
{"learn":[0.05743925455],"iteration":649,"passed_time":8.583138765,"remaining_time":4.621690104},
{"learn":[0.05743814055],"iteration":650,"passed_time":8.59378224,"remaining_time":4.607112138},
{"learn":[0.05743589043],"iteration":651,"passed_time":8.607673624,"remaining_time":4.594279787},
{"learn":[0.05743273939],"iteration":652,"passed_time":8.618315599,"remaining_time":4.579717478},
{"learn":[0.05743072675],"iteration":653,"passed_time":8.630599194,"remaining_time":4.566035659},
{"learn":[0.05742860466],"iteration":654,"passed_time":8.6431654,"remaining_time":4.552506966},
{"learn":[0.0574267618],"iteration":655,"passed_time":8.655068015,"remaining_time":4.538633228},
{"learn":[0.05742354494],"iteration":656,"passed_time":8.666120176,"remaining_time":4.524321492},
{"learn":[0.05741922431],"iteration":657,"passed_time":8.680137846,"remaining_time":4.511561008},
{"learn":[0.05741666453],"iteration":658,"passed_time":8.692121582,"remaining_time":4.497744248},
{"learn":[0.05741379366],"iteration":659,"passed_time":8.704530838,"remaining_time":4.48415225},
{"learn":[0.05741159577],"iteration":660,"passed_time":8.717564852,"remaining_time":4.470884243},
{"learn":[0.05740998956],"iteration":661,"passed_time":8.727911592,"remaining_time":4.456244891},
{"learn":[0.05740867023],"iteration":662,"passed_time":8.744064689,"remaining_time":4.444569835},
{"learn":[0.05740638579],"iteration":663,"passed_time":8.757661381,"remaining_time":4.431587687},
{"learn":[0.05740460362],"iteration":664,"passed_time":8.769246264,"remaining_time":4.417590223},
{"learn":[0.057401374],"iteration":665,"passed_time":8.782407354,"remaining_time":4.404390475},
{"learn":[0.05739871022],"iteration":666,"passed_time":8.795291459,"remaining_time":4.391052558},
{"learn":[0.05739616073],"iteration":667,"passed_time":8.808548545,"remaining_time":4.377901372},
{"learn":[0.05739293067],"iteration":668,"passed_time":8.821591308,"remaining_time":4.364643831},
{"learn":[0.0573914629],"iteration":669,"passed_time":8.835352283,"remaining_time":4.351740677},
{"learn":[0.0573879693],"iteration":670,"passed_time":8.848294635,"remaining_time":4.338433584},
{"learn":[0.05738511318],"iteration":671,"passed_time":8.861909576,"remaining_time":4.325455864},
{"learn":[0.05737821028],"iteration":672,"passed_time":8.874341497,"remaining_time":4.31190144},
{"learn":[0.05737596235],"iteration":673,"passed_time":8.885548233,"remaining_time":4.297757751},
{"learn":[0.05737407901],"iteration":674,"passed_time":8.896848422,"remaining_time":4.283667759},
{"learn":[0.05737240289],"iteration":675,"passed_time":8.910795512,"remaining_time":4.270854654},
{"learn":[0.05736957962],"iteration":676,"passed_time":8.922238236,"remaining_time":4.256843353},
{"learn":[0.05736750723],"iteration":677,"passed_time":8.93523021,"remaining_time":4.24357541},
{"learn":[0.05736527224],"iteration":678,"passed_time":8.94661427,"remaining_time":4.229548131},
{"learn":[0.05736273588],"iteration":679,"passed_time":8.960107468,"remaining_time":4.216521161},
{"learn":[0.05735983087],"iteration":680,"passed_time":8.971965169,"remaining_time":4.202726709},
{"learn":[0.05735693575],"iteration":681,"passed_time":8.984601371,"remaining_time":4.189300933},
{"learn":[0.05735400775],"iteration":682,"passed_time":8.997996865,"remaining_time":4.176229878},
{"learn":[0.05735187881],"iteration":683,"passed_time":9.010803933,"remaining_time":4.162886028},
{"learn":[0.05734649491],"iteration":684,"passed_time":9.02387707,"remaining_time":4.149666098},
{"learn":[0.0573427607],"iteration":685,"passed_time":9.037323311,"remaining_time":4.136617376},
{"learn":[0.05734089506],"iteration":686,"passed_time":9.049058186,"remaining_time":4.122787791},
{"learn":[0.05733810364],"iteration":687,"passed_time":9.062205777,"remaining_time":4.109604945},
{"learn":[0.05733386842],"iteration":688,"passed_time":9.075474403,"remaining_time":4.096476835},
{"learn":[0.05733263651],"iteration":689,"passed_time":9.08841313,"remaining_time":4.083200102},
{"learn":[0.05733032763],"iteration":690,"passed_time":9.101219656,"remaining_time":4.06986523},
{"learn":[0.05732632646],"iteration":691,"passed_time":9.114134968,"remaining_time":4.056580304},
{"learn":[0.05732208916],"iteration":692,"passed_time":9.126893038,"remaining_time":4.043226786},
{"learn":[0.05731699662],"iteration":693,"passed_time":9.139505741,"remaining_time":4.029810889},
{"learn":[0.05731473951],"iteration":694,"passed_time":9.152535422,"remaining_time":4.016580293},
{"learn":[0.05731344634],"iteration":695,"passed_time":9.164372041,"remaining_time":4.002829167},
{"learn":[0.05731081012],"iteration":696,"passed_time":9.177805283,"remaining_time":3.98977762},
{"learn":[0.05730828958],"iteration":697,"passed_time":9.191357269,"remaining_time":3.976776354},
{"learn":[0.05730400008],"iteration":698,"passed_time":9.203990055,"remaining_time":3.963377692},
{"learn":[0.05730001658],"iteration":699,"passed_time":9.21567014,"remaining_time":3.949572917},
{"learn":[0.05729682918],"iteration":700,"passed_time":9.22997517,"remaining_time":3.936893831},
{"learn":[0.05729358053],"iteration":701,"passed_time":9.24357632,"remaining_time":3.923911315},
{"learn":[0.05729168508],"iteration":702,"passed_time":9.256057238,"remaining_time":3.910453769},
{"learn":[0.05728860189],"iteration":703,"passed_time":9.267992977,"remaining_time":3.896769774},
{"learn":[0.0572867639],"iteration":704,"passed_time":9.28042744,"remaining_time":3.883299425},
{"learn":[0.05728457106],"iteration":705,"passed_time":9.291468643,"remaining_time":3.869251814},
{"learn":[0.05728163079],"iteration":706,"passed_time":9.303757988,"remaining_time":3.855729972},
{"learn":[0.05727733259],"iteration":707,"passed_time":9.317431676,"remaining_time":3.842782556},
{"learn":[0.05727533319],"iteration":708,"passed_time":9.330050378,"remaining_time":3.829400085},
{"learn":[0.05727247272],"iteration":709,"passed_time":9.341707966,"remaining_time":3.815627197},
{"learn":[0.05726884909],"iteration":710,"passed_time":9.353734158,"remaining_time":3.802010087},
{"learn":[0.05726611853],"iteration":711,"passed_time":9.365878886,"remaining_time":3.788445392},
{"learn":[0.05726513281],"iteration":712,"passed_time":9.377533181,"remaining_time":3.774687269},
{"learn":[0.05726259296],"iteration":713,"passed_time":9.388948823,"remaining_time":3.760839445},
{"learn":[0.05726111876],"iteration":714,"passed_time":9.401127716,"remaining_time":3.747302656},
{"learn":[0.05725854065],"iteration":715,"passed_time":9.413389604,"remaining_time":3.73380258},
{"learn":[0.05725541012],"iteration":716,"passed_time":9.426580276,"remaining_time":3.72067255},
{"learn":[0.05725396532],"iteration":717,"passed_time":9.437530401,"remaining_time":3.706662358},
{"learn":[0.05725187237],"iteration":718,"passed_time":9.449325689,"remaining_time":3.692990985},
{"learn":[0.05725053137],"iteration":719,"passed_time":9.460460179,"remaining_time":3.679067847},
{"learn":[0.05724906464],"iteration":720,"passed_time":9.472962471,"remaining_time":3.665681733},
{"learn":[0.05724618913],"iteration":721,"passed_time":9.48577733,"remaining_time":3.652418418},
{"learn":[0.05724399098],"iteration":722,"passed_time":9.497636323,"remaining_time":3.638790126},
{"learn":[0.05724256252],"iteration":723,"passed_time":9.509613643,"remaining_time":3.625211831},
{"learn":[0.0572390256],"iteration":724,"passed_time":9.521055158,"remaining_time":3.611434715},
{"learn":[0.05723663648],"iteration":725,"passed_time":9.535044621,"remaining_time":3.598625656},
{"learn":[0.0572347419],"iteration":726,"passed_time":9.547352298,"remaining_time":3.585181812},
{"learn":[0.05723234778],"iteration":727,"passed_time":9.558581158,"remaining_time":3.571338015},
{"learn":[0.05723009717],"iteration":728,"passed_time":9.569755604,"remaining_time":3.557481164},
{"learn":[0.0572278217],"iteration":729,"passed_time":9.580787766,"remaining_time":3.543579037},
{"learn":[0.05722437356],"iteration":730,"passed_time":9.592487726,"remaining_time":3.529930504},
{"learn":[0.05722227018],"iteration":731,"passed_time":9.604022028,"remaining_time":3.516226644},
{"learn":[0.0572208071],"iteration":732,"passed_time":9.614674961,"remaining_time":3.50220766},
{"learn":[0.05721934259],"iteration":733,"passed_time":9.627647269,"remaining_time":3.489038384},
{"learn":[0.05721793922],"iteration":734,"passed_time":9.640200809,"remaining_time":3.475718659},
{"learn":[0.05721652411],"iteration":735,"passed_time":9.652404742,"remaining_time":3.462275614},
{"learn":[0.05721507733],"iteration":736,"passed_time":9.665018694,"remaining_time":3.448982248},
{"learn":[0.05721331693],"iteration":737,"passed_time":9.677696769,"remaining_time":3.435713487},
{"learn":[0.05721048146],"iteration":738,"passed_time":9.691638484,"remaining_time":3.422892618},
{"learn":[0.05720906812],"iteration":739,"passed_time":9.703575431,"remaining_time":3.409364341},
{"learn":[0.05720597391],"iteration":740,"passed_time":9.71723862,"remaining_time":3.396443728},
{"learn":[0.05720237833],"iteration":741,"passed_time":9.729639126,"remaining_time":3.383082068},
{"learn":[0.05720084319],"iteration":742,"passed_time":9.741947011,"remaining_time":3.369690958},
{"learn":[0.05719752396],"iteration":743,"passed_time":9.754847699,"remaining_time":3.356506735},
{"learn":[0.057196036],"iteration":744,"passed_time":9.766396875,"remaining_time":3.342860675},
{"learn":[0.05719517153],"iteration":745,"passed_time":9.777417163,"remaining_time":3.32904016},
{"learn":[0.05719227959],"iteration":746,"passed_time":9.791580575,"remaining_time":3.316291681},
{"learn":[0.05719076904],"iteration":747,"passed_time":9.804419932,"remaining_time":3.303093346},
{"learn":[0.05718850431],"iteration":748,"passed_time":9.817358493,"remaining_time":3.289929215},
{"learn":[0.05718625353],"iteration":749,"passed_time":9.829699002,"remaining_time":3.276566334},
{"learn":[0.05718421577],"iteration":750,"passed_time":9.84046722,"remaining_time":3.26268487},
{"learn":[0.05718276852],"iteration":751,"passed_time":9.852577074,"remaining_time":3.249254142},
{"learn":[0.05718168457],"iteration":752,"passed_time":9.866499457,"remaining_time":3.236421469},
{"learn":[0.05717972275],"iteration":753,"passed_time":9.879472058,"remaining_time":3.223276029},
{"learn":[0.05717702954],"iteration":754,"passed_time":9.891994057,"remaining_time":3.209984826},
{"learn":[0.05717459175],"iteration":755,"passed_time":9.90586036,"remaining_time":3.197129534},
{"learn":[0.05717243544],"iteration":756,"passed_time":9.917793266,"remaining_time":3.183650943},
{"learn":[0.05717152907],"iteration":757,"passed_time":9.930332222,"remaining_time":3.170369918},
{"learn":[0.05716854512],"iteration":758,"passed_time":9.941785279,"remaining_time":3.15674605},
{"learn":[0.05716580068],"iteration":759,"passed_time":9.95348903,"remaining_time":3.143207062},
{"learn":[0.05716231766],"iteration":760,"passed_time":9.966559375,"remaining_time":3.13010209},
{"learn":[0.05716072482],"iteration":761,"passed_time":9.979862124,"remaining_time":3.117069797},
{"learn":[0.05715851841],"iteration":762,"passed_time":9.991940481,"remaining_time":3.10365648},
{"learn":[0.05715557784],"iteration":763,"passed_time":10.00519836,"remaining_time":3.090611011},
{"learn":[0.05715362629],"iteration":764,"passed_time":10.01810617,"remaining_time":3.077457451},
{"learn":[0.05715073136],"iteration":765,"passed_time":10.03162699,"remaining_time":3.064491796},
{"learn":[0.05714686882],"iteration":766,"passed_time":10.04285802,"remaining_time":3.050829098},
{"learn":[0.05714448818],"iteration":767,"passed_time":10.05475413,"remaining_time":3.037373644},
{"learn":[0.0571412403],"iteration":768,"passed_time":10.06651359,"remaining_time":3.023881195},
{"learn":[0.05713857716],"iteration":769,"passed_time":10.0799255,"remaining_time":3.010886838},
{"learn":[0.05713654266],"iteration":770,"passed_time":10.09280502,"remaining_time":2.997733269},
{"learn":[0.05713405073],"iteration":771,"passed_time":10.10469501,"remaining_time":2.984288165},
{"learn":[0.05713070701],"iteration":772,"passed_time":10.1171816,"remaining_time":2.97102228},
{"learn":[0.05712893207],"iteration":773,"passed_time":10.12891743,"remaining_time":2.957539198},
{"learn":[0.05712744343],"iteration":774,"passed_time":10.14302547,"remaining_time":2.94474933},
{"learn":[0.05712470118],"iteration":775,"passed_time":10.15598836,"remaining_time":2.931625507},
{"learn":[0.05712320523],"iteration":776,"passed_time":10.16709215,"remaining_time":2.917968531},
{"learn":[0.05712017821],"iteration":777,"passed_time":10.18010754,"remaining_time":2.90486359},
{"learn":[0.05711758556],"iteration":778,"passed_time":10.19373494,"remaining_time":2.891932504},
{"learn":[0.05711632563],"iteration":779,"passed_time":10.20598616,"remaining_time":2.87861148},
{"learn":[0.05711332098],"iteration":780,"passed_time":10.2181888,"remaining_time":2.865279574},
{"learn":[0.05711160435],"iteration":781,"passed_time":10.23121448,"remaining_time":2.852179996},
{"learn":[0.05711036299],"iteration":782,"passed_time":10.24163472,"remaining_time":2.838358536},
{"learn":[0.05710913419],"iteration":783,"passed_time":10.25377649,"remaining_time":2.825020052},
{"learn":[0.05710632977],"iteration":784,"passed_time":10.26621036,"remaining_time":2.811764622},
{"learn":[0.05710207621],"iteration":785,"passed_time":10.27985643,"remaining_time":2.798841318},
{"learn":[0.05710039518],"iteration":786,"passed_time":10.29175771,"remaining_time":2.785443955},
{"learn":[0.05709787679],"iteration":787,"passed_time":10.30403952,"remaining_time":2.772152763},
{"learn":[0.0570960371],"iteration":788,"passed_time":10.31543033,"remaining_time":2.758625854},
{"learn":[0.0570928257],"iteration":789,"passed_time":10.32795312,"remaining_time":2.745405259},
{"learn":[0.05709118928],"iteration":790,"passed_time":10.33903703,"remaining_time":2.731806243},
{"learn":[0.05708883113],"iteration":791,"passed_time":10.35276429,"remaining_time":2.718907794},
{"learn":[0.05708475401],"iteration":792,"passed_time":10.3654037,"remaining_time":2.705723287},
{"learn":[0.05708281665],"iteration":793,"passed_time":10.37776896,"remaining_time":2.692469025},
{"learn":[0.0570817769],"iteration":794,"passed_time":10.3922544,"remaining_time":2.679763713},
{"learn":[0.05707986067],"iteration":795,"passed_time":10.40754683,"remaining_time":2.667260746},
{"learn":[0.05707792959],"iteration":796,"passed_time":10.41941878,"remaining_time":2.653879565},
{"learn":[0.0570762952],"iteration":797,"passed_time":10.4317128,"remaining_time":2.640609003},
{"learn":[0.05707558988],"iteration":798,"passed_time":10.4432106,"remaining_time":2.627140589},
{"learn":[0.05707343738],"iteration":799,"passed_time":10.45421618,"remaining_time":2.613554045},
{"learn":[0.05707230223],"iteration":800,"passed_time":10.46571002,"remaining_time":2.60009525},
{"learn":[0.05706948173],"iteration":801,"passed_time":10.47954445,"remaining_time":2.587219204},
{"learn":[0.05706621994],"iteration":802,"passed_time":10.49178422,"remaining_time":2.573949553},
{"learn":[0.05706292406],"iteration":803,"passed_time":10.50510872,"remaining_time":2.560946901},
{"learn":[0.05706001792],"iteration":804,"passed_time":10.51874466,"remaining_time":2.548018892},
{"learn":[0.05705848296],"iteration":805,"passed_time":10.53069815,"remaining_time":2.534684169},
{"learn":[0.05705671349],"iteration":806,"passed_time":10.54168577,"remaining_time":2.521121875},
{"learn":[0.05705515248],"iteration":807,"passed_time":10.55470037,"remaining_time":2.508047612},
{"learn":[0.05705203592],"iteration":808,"passed_time":10.56723545,"remaining_time":2.494860285},
{"learn":[0.05705048362],"iteration":809,"passed_time":10.57976741,"remaining_time":2.481673836},
{"learn":[0.05704779656],"iteration":810,"passed_time":10.59306315,"remaining_time":2.468666999},
{"learn":[0.05704567831],"iteration":811,"passed_time":10.60515384,"remaining_time":2.455380447},
{"learn":[0.05704189412],"iteration":812,"passed_time":10.61757856,"remaining_time":2.442173666},
{"learn":[0.05703645297],"iteration":813,"passed_time":10.63086152,"remaining_time":2.429164916},
{"learn":[0.05703484049],"iteration":814,"passed_time":10.64305645,"remaining_time":2.415908519},
{"learn":[0.05703275839],"iteration":815,"passed_time":10.65495494,"remaining_time":2.402587879},
{"learn":[0.05703159171],"iteration":816,"passed_time":10.6651574,"remaining_time":2.388890824},
{"learn":[0.05702989465],"iteration":817,"passed_time":10.67859335,"remaining_time":2.375921747},
{"learn":[0.05702887203],"iteration":818,"passed_time":10.69135317,"remaining_time":2.362802104},
{"learn":[0.05702692297],"iteration":819,"passed_time":10.70453576,"remaining_time":2.349776142},
{"learn":[0.05702577525],"iteration":820,"passed_time":10.71601219,"remaining_time":2.336377809},
{"learn":[0.05702513963],"iteration":821,"passed_time":10.72735071,"remaining_time":2.322954289},
{"learn":[0.05702137587],"iteration":822,"passed_time":10.74001012,"remaining_time":2.309819916},
{"learn":[0.05701845163],"iteration":823,"passed_time":10.75368897,"remaining_time":2.29690444},
{"learn":[0.05701546974],"iteration":824,"passed_time":10.7662133,"remaining_time":2.283742216},
{"learn":[0.05701185809],"iteration":825,"passed_time":10.77983516,"remaining_time":2.270812733},
{"learn":[0.05701076464],"iteration":826,"passed_time":10.79277576,"remaining_time":2.257739065},
{"learn":[0.05700960955],"iteration":827,"passed_time":10.80485087,"remaining_time":2.244485929},
{"learn":[0.05700706941],"iteration":828,"passed_time":10.81620843,"remaining_time":2.231087625},
{"learn":[0.05700526039],"iteration":829,"passed_time":10.82846857,"remaining_time":2.217879104},
{"learn":[0.05700314178],"iteration":830,"passed_time":10.84181632,"remaining_time":2.204894052},
{"learn":[0.0569995038],"iteration":831,"passed_time":10.85324362,"remaining_time":2.191520347},
{"learn":[0.05699829117],"iteration":832,"passed_time":10.86588616,"remaining_time":2.178394944},
{"learn":[0.05699771058],"iteration":833,"passed_time":10.87688336,"remaining_time":2.164943211},
{"learn":[0.05699661322],"iteration":834,"passed_time":10.88772383,"remaining_time":2.151466385},
{"learn":[0.05699379249],"iteration":835,"passed_time":10.89960299,"remaining_time":2.138199629},
{"learn":[0.05699241105],"iteration":836,"passed_time":10.9124408,"remaining_time":2.12512288},
{"learn":[0.05699035475],"iteration":837,"passed_time":10.92323698,"remaining_time":2.111652017},
{"learn":[0.05698783605],"iteration":838,"passed_time":10.93383087,"remaining_time":2.098148713},
{"learn":[0.05698485153],"iteration":839,"passed_time":10.94670423,"remaining_time":2.085086519},
{"learn":[0.05698281804],"iteration":840,"passed_time":10.95818216,"remaining_time":2.071760955},
{"learn":[0.05698173943],"iteration":841,"passed_time":10.97032384,"remaining_time":2.058564331},
{"learn":[0.0569810765],"iteration":842,"passed_time":10.98135825,"remaining_time":2.045163993},
{"learn":[0.05698045529],"iteration":843,"passed_time":10.99296468,"remaining_time":2.031874988},
{"learn":[0.05697629093],"iteration":844,"passed_time":11.00370086,"remaining_time":2.018430334},
{"learn":[0.05697560499],"iteration":845,"passed_time":11.01363949,"remaining_time":2.004846905},
{"learn":[0.05697415755],"iteration":846,"passed_time":11.02764191,"remaining_time":1.992006154},
{"learn":[0.05697303284],"iteration":847,"passed_time":11.03878165,"remaining_time":1.978649541},
{"learn":[0.05696910355],"iteration":848,"passed_time":11.05012726,"remaining_time":1.965334765},
{"learn":[0.05696624102],"iteration":849,"passed_time":11.06207095,"remaining_time":1.952130168},
{"learn":[0.05696470337],"iteration":850,"passed_time":11.07620091,"remaining_time":1.939311322},
{"learn":[0.0569634749],"iteration":851,"passed_time":11.08939616,"remaining_time":1.926327033},
{"learn":[0.05696141634],"iteration":852,"passed_time":11.1031081,"remaining_time":1.91343129},
{"learn":[0.05696037968],"iteration":853,"passed_time":11.11373449,"remaining_time":1.900006131},
{"learn":[0.05695909071],"iteration":854,"passed_time":11.12533321,"remaining_time":1.886752415},
{"learn":[0.05695720614],"iteration":855,"passed_time":11.13739211,"remaining_time":1.87357998},
{"learn":[0.05695588125],"iteration":856,"passed_time":11.14890478,"remaining_time":1.860319001},
{"learn":[0.05695529854],"iteration":857,"passed_time":11.1595553,"remaining_time":1.846919409},
{"learn":[0.05695242797],"iteration":858,"passed_time":11.17187973,"remaining_time":1.833800979},
{"learn":[0.05695092896],"iteration":859,"passed_time":11.18342461,"remaining_time":1.820557495},
{"learn":[0.05694910551],"iteration":860,"passed_time":11.19505699,"remaining_time":1.807332081},
{"learn":[0.05694556302],"iteration":861,"passed_time":11.20658059,"remaining_time":1.794092948},
{"learn":[0.05694381337],"iteration":862,"passed_time":11.21871186,"remaining_time":1.780954257},
{"learn":[0.05694139888],"iteration":863,"passed_time":11.23102649,"remaining_time":1.767846762},
{"learn":[0.05693884528],"iteration":864,"passed_time":11.24263779,"remaining_time":1.754631331},
{"learn":[0.05693583953],"iteration":865,"passed_time":11.25448899,"remaining_time":1.741456726},
{"learn":[0.05693377674],"iteration":866,"passed_time":11.26788223,"remaining_time":1.728521727},
{"learn":[0.05693240643],"iteration":867,"passed_time":11.27840067,"remaining_time":1.71514849},
{"learn":[0.05692870726],"iteration":868,"passed_time":11.29170217,"remaining_time":1.702201363},
{"learn":[0.05692600675],"iteration":869,"passed_time":11.30503725,"remaining_time":1.68925844},
{"learn":[0.05692313112],"iteration":870,"passed_time":11.31655022,"remaining_time":1.676044752},
{"learn":[0.05692039545],"iteration":871,"passed_time":11.32960536,"remaining_time":1.663061338},
{"learn":[0.05691865009],"iteration":872,"passed_time":11.34219898,"remaining_time":1.65001062},
{"learn":[0.05691768046],"iteration":873,"passed_time":11.35349626,"remaining_time":1.63677406},
{"learn":[0.05691547225],"iteration":874,"passed_time":11.3642821,"remaining_time":1.623468871},
{"learn":[0.05691283233],"iteration":875,"passed_time":11.37558295,"remaining_time":1.610242336},
{"learn":[0.05691102771],"iteration":876,"passed_time":11.3882684,"remaining_time":1.597214383},
{"learn":[0.05691010164],"iteration":877,"passed_time":11.4011243,"remaining_time":1.584210894},
{"learn":[0.05690942311],"iteration":878,"passed_time":11.41384896,"remaining_time":1.571189674},
{"learn":[0.05690780564],"iteration":879,"passed_time":11.42722095,"remaining_time":1.558257403},
{"learn":[0.05690605424],"iteration":880,"passed_time":11.43979699,"remaining_time":1.54521662},
{"learn":[0.05690411072],"iteration":881,"passed_time":11.45158953,"remaining_time":1.532072068},
{"learn":[0.05690320029],"iteration":882,"passed_time":11.4652378,"remaining_time":1.51917647},
{"learn":[0.05690126214],"iteration":883,"passed_time":11.47819149,"remaining_time":1.506188023},
{"learn":[0.05689899869],"iteration":884,"passed_time":11.4907829,"remaining_time":1.49315258},
{"learn":[0.05689676413],"iteration":885,"passed_time":11.5038527,"remaining_time":1.480179693},
{"learn":[0.05689370992],"iteration":886,"passed_time":11.51668223,"remaining_time":1.467175977},
{"learn":[0.05689164209],"iteration":887,"passed_time":11.52818503,"remaining_time":1.454005319},
{"learn":[0.05688988276],"iteration":888,"passed_time":11.54041446,"remaining_time":1.44092914},
{"learn":[0.05688827321],"iteration":889,"passed_time":11.55325536,"remaining_time":1.427930438},
{"learn":[0.05688601696],"iteration":890,"passed_time":11.56490836,"remaining_time":1.41478677},
{"learn":[0.05688459457],"iteration":891,"passed_time":11.5774554,"remaining_time":1.40175469},
{"learn":[0.05688071654],"iteration":892,"passed_time":11.58957297,"remaining_time":1.388672237},
{"learn":[0.05687853329],"iteration":893,"passed_time":11.60284168,"remaining_time":1.375728431},
{"learn":[0.0568767377],"iteration":894,"passed_time":11.61754027,"remaining_time":1.362951652},
{"learn":[0.05687524804],"iteration":895,"passed_time":11.63051841,"remaining_time":1.349970887},
{"learn":[0.05687286506],"iteration":896,"passed_time":11.64334081,"remaining_time":1.336972245},
{"learn":[0.05687203847],"iteration":897,"passed_time":11.65578644,"remaining_time":1.323931199},
{"learn":[0.05687086006],"iteration":898,"passed_time":11.66771918,"remaining_time":1.310833856},
{"learn":[0.05686891773],"iteration":899,"passed_time":11.68022651,"remaining_time":1.297802946},
{"learn":[0.05686660934],"iteration":900,"passed_time":11.69452592,"remaining_time":1.284970106},
{"learn":[0.05686263209],"iteration":901,"passed_time":11.70740673,"remaining_time":1.271979889},
{"learn":[0.0568615506],"iteration":902,"passed_time":11.71933934,"remaining_time":1.258888058},
{"learn":[0.05685914976],"iteration":903,"passed_time":11.73228553,"remaining_time":1.245906428},
{"learn":[0.05685824928],"iteration":904,"passed_time":11.74389553,"remaining_time":1.232784614},
{"learn":[0.05685732277],"iteration":905,"passed_time":11.7578045,"remaining_time":1.219904661},
{"learn":[0.05685564834],"iteration":906,"passed_time":11.77069469,"remaining_time":1.206917978},
{"learn":[0.05685432733],"iteration":907,"passed_time":11.78365437,"remaining_time":1.193938549},
{"learn":[0.05685230187],"iteration":908,"passed_time":11.79593505,"remaining_time":1.180891188},
{"learn":[0.05684835361],"iteration":909,"passed_time":11.80917181,"remaining_time":1.167940069},
{"learn":[0.05684456153],"iteration":910,"passed_time":11.82252047,"remaining_time":1.154999256},
{"learn":[0.05684234914],"iteration":911,"passed_time":11.83314657,"remaining_time":1.141794844},
{"learn":[0.05684089823],"iteration":912,"passed_time":11.84714316,"remaining_time":1.128917256},
{"learn":[0.05683797951],"iteration":913,"passed_time":11.85893174,"remaining_time":1.115829463},
{"learn":[0.05683754611],"iteration":914,"passed_time":11.87035955,"remaining_time":1.102710996},
{"learn":[0.05683630805],"iteration":915,"passed_time":11.88165515,"remaining_time":1.089584097},
{"learn":[0.05683586175],"iteration":916,"passed_time":11.89264398,"remaining_time":1.076433425},
{"learn":[0.05683413006],"iteration":917,"passed_time":11.90336995,"remaining_time":1.063263983},
{"learn":[0.05683279342],"iteration":918,"passed_time":11.91470547,"remaining_time":1.050153584},
{"learn":[0.05683188837],"iteration":919,"passed_time":11.92661296,"remaining_time":1.037096779},
{"learn":[0.0568311255],"iteration":920,"passed_time":11.93804161,"remaining_time":1.024001397},
{"learn":[0.05682811959],"iteration":921,"passed_time":11.95070531,"remaining_time":1.011014115},
{"learn":[0.05682593811],"iteration":922,"passed_time":11.96263117,"remaining_time":0.9979659806},
{"learn":[0.05682435873],"iteration":923,"passed_time":11.97463745,"remaining_time":0.9849268895},
{"learn":[0.05682345614],"iteration":924,"passed_time":11.98723661,"remaining_time":0.9719381034},
{"learn":[0.05682149016],"iteration":925,"passed_time":12.00109383,"remaining_time":0.9590506947},
{"learn":[0.05682002617],"iteration":926,"passed_time":12.01286262,"remaining_time":0.9459967326},
{"learn":[0.05681794485],"iteration":927,"passed_time":12.02408377,"remaining_time":0.9329030511},
{"learn":[0.05681570553],"iteration":928,"passed_time":12.03771317,"remaining_time":0.9199974542},
{"learn":[0.05681282847],"iteration":929,"passed_time":12.0500463,"remaining_time":0.9069927325},
{"learn":[0.05681050712],"iteration":930,"passed_time":12.06272842,"remaining_time":0.8940153178},
{"learn":[0.05680856651],"iteration":931,"passed_time":12.07547724,"remaining_time":0.8810434037},
{"learn":[0.0568080211],"iteration":932,"passed_time":12.08761684,"remaining_time":0.8680282191},
{"learn":[0.05680593205],"iteration":933,"passed_time":12.1011607,"remaining_time":0.8551141397},
{"learn":[0.05680541671],"iteration":934,"passed_time":12.11204275,"remaining_time":0.842013667},
{"learn":[0.0568046214],"iteration":935,"passed_time":12.12211313,"remaining_time":0.8288624362},
{"learn":[0.05680345694],"iteration":936,"passed_time":12.13552333,"remaining_time":0.8159423371},
{"learn":[0.05680218693],"iteration":937,"passed_time":12.14615989,"remaining_time":0.8028378605},
{"learn":[0.05680015075],"iteration":938,"passed_time":12.15902612,"remaining_time":0.789883486},
{"learn":[0.0567959786],"iteration":939,"passed_time":12.17325749,"remaining_time":0.7770164353},
{"learn":[0.05679339691],"iteration":940,"passed_time":12.18584027,"remaining_time":0.7640431203},
{"learn":[0.05679284292],"iteration":941,"passed_time":12.19648562,"remaining_time":0.7509513442},
{"learn":[0.05679050355],"iteration":942,"passed_time":12.20906937,"remaining_time":0.7379819238},
{"learn":[0.05678942329],"iteration":943,"passed_time":12.21994504,"remaining_time":0.7249119939},
{"learn":[0.05678557156],"iteration":944,"passed_time":12.23212302,"remaining_time":0.7119225036},
{"learn":[0.05678401762],"iteration":945,"passed_time":12.24239626,"remaining_time":0.6988260022},
{"learn":[0.0567812801],"iteration":946,"passed_time":12.25478564,"remaining_time":0.6858538955},
{"learn":[0.0567786899],"iteration":947,"passed_time":12.26876586,"remaining_time":0.672970279},
{"learn":[0.05677752745],"iteration":948,"passed_time":12.28303572,"remaining_time":0.6600999175},
{"learn":[0.05677644104],"iteration":949,"passed_time":12.29619298,"remaining_time":0.6471680514},
{"learn":[0.05677508633],"iteration":950,"passed_time":12.30883668,"remaining_time":0.6342092505},
{"learn":[0.056772662],"iteration":951,"passed_time":12.32134705,"remaining_time":0.6212443892},
{"learn":[0.05677099058],"iteration":952,"passed_time":12.33473967,"remaining_time":0.6083239923},
{"learn":[0.0567690529],"iteration":953,"passed_time":12.34598687,"remaining_time":0.595299157},
{"learn":[0.05676642546],"iteration":954,"passed_time":12.35829629,"remaining_time":0.5823280976},
{"learn":[0.05676528798],"iteration":955,"passed_time":12.37200627,"remaining_time":0.5694228827},
{"learn":[0.05676321464],"iteration":956,"passed_time":12.38459114,"remaining_time":0.5564654327},
{"learn":[0.05676150515],"iteration":957,"passed_time":12.39681341,"remaining_time":0.5434928633},
{"learn":[0.05675999557],"iteration":958,"passed_time":12.40706019,"remaining_time":0.5304374014},
{"learn":[0.05675850083],"iteration":959,"passed_time":12.41883994,"remaining_time":0.5174516642},
{"learn":[0.05675491651],"iteration":960,"passed_time":12.43293652,"remaining_time":0.5045624604},
{"learn":[0.05675349512],"iteration":961,"passed_time":12.44330243,"remaining_time":0.4915233808},
{"learn":[0.05675273462],"iteration":962,"passed_time":12.45516217,"remaining_time":0.4785472486},
{"learn":[0.05675184981],"iteration":963,"passed_time":12.4671947,"remaining_time":0.465579885},
{"learn":[0.05675072478],"iteration":964,"passed_time":12.48101509,"remaining_time":0.4526793036},
{"learn":[0.05674811833],"iteration":965,"passed_time":12.49268109,"remaining_time":0.4397009907},
{"learn":[0.05674468514],"iteration":966,"passed_time":12.5042751,"remaining_time":0.426722935},
{"learn":[0.05674397459],"iteration":967,"passed_time":12.51649961,"remaining_time":0.4137685822},
{"learn":[0.05674194517],"iteration":968,"passed_time":12.52823678,"remaining_time":0.4008001446},
{"learn":[0.05674044951],"iteration":969,"passed_time":12.54116371,"remaining_time":0.3878710427},
{"learn":[0.05673665132],"iteration":970,"passed_time":12.55504797,"remaining_time":0.3749705368},
{"learn":[0.05673470819],"iteration":971,"passed_time":12.5683761,"remaining_time":0.3620519863},
{"learn":[0.05673326862],"iteration":972,"passed_time":12.57939818,"remaining_time":0.3490686031},
{"learn":[0.05672944912],"iteration":973,"passed_time":12.59058554,"remaining_time":0.3360936591},
{"learn":[0.05672696883],"iteration":974,"passed_time":12.60466137,"remaining_time":0.3231964454},
{"learn":[0.05672517236],"iteration":975,"passed_time":12.61635225,"remaining_time":0.3102381701},
{"learn":[0.05672369153],"iteration":976,"passed_time":12.62897737,"remaining_time":0.2973044826},
{"learn":[0.05672225373],"iteration":977,"passed_time":12.64201601,"remaining_time":0.2843807282},
{"learn":[0.05671900852],"iteration":978,"passed_time":12.65460813,"remaining_time":0.2714471611},
{"learn":[0.05671633823],"iteration":979,"passed_time":12.66732799,"remaining_time":0.2585168978},
{"learn":[0.05671503278],"iteration":980,"passed_time":12.67986945,"remaining_time":0.2455836081},
{"learn":[0.05671297567],"iteration":981,"passed_time":12.69135609,"remaining_time":0.2326317816},
{"learn":[0.05671080621],"iteration":982,"passed_time":12.70475304,"remaining_time":0.2197159732},
{"learn":[0.05670991744],"iteration":983,"passed_time":12.71715825,"remaining_time":0.206783061},
{"learn":[0.05670838518],"iteration":984,"passed_time":12.73042221,"remaining_time":0.1938642976},
{"learn":[0.05670667511],"iteration":985,"passed_time":12.74511097,"remaining_time":0.1809650645},
{"learn":[0.05670525597],"iteration":986,"passed_time":12.75578428,"remaining_time":0.1680093167},
{"learn":[0.05670381597],"iteration":987,"passed_time":12.7709448,"remaining_time":0.1551126899},
{"learn":[0.05670269254],"iteration":988,"passed_time":12.78266722,"remaining_time":0.1421732451},
{"learn":[0.05670009099],"iteration":989,"passed_time":12.79455317,"remaining_time":0.1292379108},
{"learn":[0.05669655893],"iteration":990,"passed_time":12.80764835,"remaining_time":0.1163156762},
{"learn":[0.05669488642],"iteration":991,"passed_time":12.82029692,"remaining_time":0.1033894913},
{"learn":[0.05669150081],"iteration":992,"passed_time":12.83380637,"remaining_time":0.09046993412},
{"learn":[0.05669041354],"iteration":993,"passed_time":12.84587785,"remaining_time":0.07754051017},
{"learn":[0.05668818566],"iteration":994,"passed_time":12.85976765,"remaining_time":0.064621948},
{"learn":[0.05668644696],"iteration":995,"passed_time":12.8723394,"remaining_time":0.05169614216},
{"learn":[0.05668407575],"iteration":996,"passed_time":12.88412035,"remaining_time":0.03876866706},
{"learn":[0.05668276458],"iteration":997,"passed_time":12.89490145,"remaining_time":0.02584148587},
{"learn":[0.05668112448],"iteration":998,"passed_time":12.9070553,"remaining_time":0.01291997527},
{"learn":[0.0566782844],"iteration":999,"passed_time":12.92072082,"remaining_time":0}
]}